{"storyMeta":{"storyReviewType":"NONE","storyId":"story_breeze_set_2_story_1","storyGroup":"story_breeze_set_2","storySort":0,"storyDependence":null,"storyCanShow":0,"storyCode":null,"storyName":"囚徒的幻梦","storyPic":null,"storyInfo":"收到儿时玩伴的求助后，格蕾丝便在难民队伍中寻找她的踪影，并开始想方设法地帮助这些人，但身为贵族千金的她却遇到了由身份带来的阻力。她终究要被迫做出选择，这即是亚利桑那的宿命。","storyCanEnter":0,"storyTxt":"obt/memory/story_breeze_2_1","avgTag":"幕间","unLockType":"STAGE_CLEAR","costItemType":"NONE","costItemId":null,"costItemCount":0,"stageCount":0,"requiredStages":null,"characters":["管家","女仆","？？？","格蕾丝","聒噪的老人","彬彬有礼的先生","医生","陌生的镇民","聚集起来的镇民们"]},"lines":[{"type":"header","key":"title_test","skippable":"true","mode":"BLACK_MASK","id":0},{"type":"blocker","a":"1","r":"0","g":"0","b":"0","fadetime":"0","block":"true","id":1},{"type":"stopmusic","id":2},{"type":"dialog","id":3},{"type":"background","image":"https://media.prts.wiki/b/bb/Avg_bg_bg_ltroom.png","screenadapt":"coverall","id":4},{"type":"delay","time":"1","id":5},{"type":"playmusic","key":"https://static.prts.wiki/music/music/avg/m_avg_normal_loop.mp3","volume":"0.6","text":"","id":6,"musicid":0},{"type":"blocker","a":"0","r":"0","g":"0","b":"0","fadetime":"1","block":"true","id":7},{"type":"delay","time":"2","id":8},{"type":"text","text":"07:22 A.M.","id":9},{"type":"text","text":"多伦郡，岩溪镇北，亚利桑那宅邸","id":10},{"type":"dialog","id":11},{"type":"playsound","key":"$d_gen_walk_n","id":12},{"type":"character","name":"avg_npc_177","fadetime":"1.5","id":13},{"type":"delay","time":"2","id":14},{"type":"playsound","key":"$doorknockquite","volume":"0.7","id":15},{"type":"delay","time":"0.5","text":"","id":16},{"type":"character","name":"avg_npc_177","id":17},{"type":"dialogue","name":"管家","text":"咳咳......","id":18,"figure":"https://media.prts.wiki/a/ae/Avg_avg_npc_177.png"},{"type":"dialogue","name":"管家","text":"小姐，有您的信件。","id":19,"figure":"https://media.prts.wiki/a/ae/Avg_avg_npc_177.png"},{"type":"dialog","id":20},{"type":"character","id":21},{"type":"playsound","key":"$dooropenquite","volume":"0.5","id":22},{"type":"character","name":"avg_npc_243","fadetime":"1.5","id":23},{"type":"delay","time":"2","text":"","id":24},{"type":"character","name":"avg_npc_243","name2":"avg_npc_177","focus":"1","id":25},{"type":"dialogue","name":"女仆","text":"小姐正在更衣。","id":26,"figure":"https://media.prts.wiki/5/5e/Avg_avg_npc_243.png"},{"type":"character","name":"avg_npc_243","name2":"avg_npc_177","focus":"2","id":27},{"type":"dialogue","name":"管家","text":"老爷夫人不在这几天，她几乎每天都要偷偷跑出去，我们不该做点什么吗？","id":28,"figure":"https://media.prts.wiki/a/ae/Avg_avg_npc_177.png"},{"type":"character","name":"avg_npc_243","name2":"avg_npc_177","focus":"1","id":29},{"type":"dialogue","name":"女仆","text":"要不你把窗外那棵树砍了。如果要我在衣服上约束她，该尝试的我都尝试过了，放弃吧。","id":30,"figure":"https://media.prts.wiki/5/5e/Avg_avg_npc_243.png"},{"type":"character","name":"avg_npc_243","name2":"avg_npc_177","focus":"2","id":31},{"type":"dialogue","name":"管家","text":"我没有看到你在努力。","id":32,"figure":"https://media.prts.wiki/a/ae/Avg_avg_npc_177.png"},{"type":"character","name":"avg_npc_243","name2":"avg_npc_177","focus":"1","id":33},{"type":"dialogue","name":"女仆","text":"不用拐弯抹角地暗示我帮你找个眼科医生的，康塞尔先生。","id":34,"figure":"https://media.prts.wiki/5/5e/Avg_avg_npc_243.png"},{"type":"dialog","id":35},{"type":"blocker","a":"0","r":"0","g":"0","b":"0","fadetime":"0","block":"true","id":36},{"type":"blocker","a":"1","r":"0","g":"0","b":"0","fadetime":"2","block":"true","id":37},{"type":"character","id":38},{"type":"background","image":"https://media.prts.wiki/2/2e/Avg_bg_32_g11_victoriaroom_n.png","screenadapt":"showall","id":39},{"type":"delay","time":"2","id":40},{"type":"blocker","a":"0","r":"0","g":"0","b":"0","fadetime":"2","block":"true","id":41},{"type":"delay","time":"2","text":"","id":42},{"type":"playsound","key":"$doorclosequite","volume":"0.7","id":43},{"type":"delay","time":"1","id":44},{"type":"playsound","key":"$d_gen_walk_n","id":45},{"type":"character","name":"avg_npc_243","fadetime":"1.5","id":46},{"type":"delay","time":"2","id":47},{"type":"dialogue","name":"女仆","text":"小姐，您的信。","id":48,"figure":"https://media.prts.wiki/5/5e/Avg_avg_npc_243.png"},{"type":"dialog","id":49},{"type":"character","id":50},{"type":"dialogue","name":"？？？","text":"放桌上吧。","id":51},{"type":"dialog","id":52},{"type":"character","name":"avg_npc_243","id":53},{"type":"dialogue","name":"女仆","text":"您不想读一读吗？","id":54,"figure":"https://media.prts.wiki/5/5e/Avg_avg_npc_243.png"},{"type":"dialog","id":55},{"type":"character","id":56},{"type":"dialogue","name":"？？？","text":"不用，我都能猜到里面的内容。","id":57},{"type":"dialog","id":58},{"type":"character","name":"char_empty","id":59},{"type":"delay","time":"0.2","id":60},{"type":"move","name":"middle","ypos":"-50","fadetime":"0.5","isblock":"true","id":61},{"type":"delay","time":"0.6","id":62},{"type":"character","name":"avgnew_275_breeze_1#4$1","fadetime":"1.5","id":63},{"type":"delay","time":"2","id":64},{"type":"dialogue","name":"格蕾丝","text":"首先是向我问好，接着询问老爹老妈的近况，最后再找一些理由，十分痛苦地拒绝我的请求......","id":65,"figure":"https://media.prts.wiki/0/0d/Avg_avgnew_275_breeze_1-4$1.png"},{"type":"text","text":"年轻的沃尔珀坐在梳妆台前，闷闷不乐地摆弄着手上的收信器，上面的指示灯正闪着红光。","id":66},{"type":"text","text":"若是在昨天或者前天闪烁，她应当会欣喜若狂。","id":67},{"type":"dialogue","name":"格蕾丝","text":"唉......","id":68,"figure":"https://media.prts.wiki/0/0d/Avg_avgnew_275_breeze_1-4$1.png"},{"type":"dialogue","name":"格蕾丝","text":"我现在觉得，不该花那么多时间写信，也不该花那么多时间来看回信。","id":69,"figure":"https://media.prts.wiki/0/0d/Avg_avgnew_275_breeze_1-4$1.png"},{"type":"dialog","id":70},{"type":"playsound","key":"$d_avg_clothmovement","volume":"0.7","id":71},{"type":"move","name":"middle","ypos":"50","fadetime":"1.5","isblock":"true","id":72},{"type":"delay","time":"1.5","text":"","id":73},{"type":"character","name":"avgnew_275_breeze_1#2$1","id":74},{"type":"dialogue","name":"格蕾丝","text":"对了，老爹老妈什么时候回来？我得提前下楼等着了。","id":75,"figure":"https://media.prts.wiki/e/ed/Avg_avgnew_275_breeze_1-2$1.png"},{"type":"character","name":"avg_npc_243","id":76},{"type":"dialogue","name":"女仆","text":"啊！抱歉，我们楼下太忙，忘记告诉您了！","id":77,"figure":"https://media.prts.wiki/5/5e/Avg_avg_npc_243.png"},{"type":"dialogue","name":"女仆","text":"老爷昨天派人通知我们，他和夫人受邀出席一家书店的剪彩仪式，听说酬劳还挺丰厚的。","id":78,"figure":"https://media.prts.wiki/5/5e/Avg_avg_npc_243.png"},{"type":"character","name":"avgnew_275_breeze_1#4$1","id":79},{"type":"dialogue","name":"格蕾丝","text":"他就应该用他的笔名，那比亚利桑那男爵的身份更值钱。","id":80,"figure":"https://media.prts.wiki/0/0d/Avg_avgnew_275_breeze_1-4$1.png"},{"type":"character","name":"avg_npc_243","id":81},{"type":"dialogue","name":"女仆","text":"老爷还用那个笔名时，有些愤世嫉俗。所以当他选择成为亨利·亚利桑那爵士后，他就不再用那个笔名写作。","id":82,"figure":"https://media.prts.wiki/5/5e/Avg_avg_npc_243.png"},{"type":"dialogue","name":"女仆","text":"这样会安全一点。老天爷，我想他也不知道他批评的那些事情，有多少贵族参与其中哩！","id":83,"figure":"https://media.prts.wiki/5/5e/Avg_avg_npc_243.png"},{"type":"character","name":"avgnew_275_breeze_1#5$1","id":84},{"type":"dialogue","name":"格蕾丝","text":"他倒是可以给自己选一种身份，而我却要按他为我选的方式生活。","id":85,"figure":"https://media.prts.wiki/0/07/Avg_avgnew_275_breeze_1-5$1.png"},{"type":"dialog","id":86},{"type":"delay","time":"1","id":87},{"type":"character","name":"avgnew_275_breeze_1#2$1","id":88},{"type":"dialogue","name":"格蕾丝","text":"等等，他们要晚多久回来？","id":89,"figure":"https://media.prts.wiki/e/ed/Avg_avgnew_275_breeze_1-2$1.png"},{"type":"character","name":"avg_npc_243","id":90},{"type":"dialogue","name":"女仆","text":"一天。","id":91,"figure":"https://media.prts.wiki/5/5e/Avg_avg_npc_243.png"},{"type":"dialog","id":92},{"type":"stopmusic","fadetime":"1","id":93},{"type":"character","name":"avgnew_275_breeze_1#2$1","id":94},{"type":"delay","time":"1.5","id":95},{"type":"character","name":"avgnew_275_breeze_1#1$1","id":96},{"type":"delay","time":"1.5","id":97},{"type":"character","name":"avgnew_275_breeze_1#6$1","id":98},{"type":"delay","time":"2","id":99},{"type":"character","name":"avg_npc_243","id":100},{"type":"dialogue","name":"女仆","text":"小姐，您这样笑我会误以为您又要偷溜出去了。","id":101,"figure":"https://media.prts.wiki/5/5e/Avg_avg_npc_243.png"},{"type":"character","name":"avgnew_275_breeze_1#6$1","id":102},{"type":"dialogue","name":"格蕾丝","text":"抱歉啦，我突然想到一件很紧急的事！","id":103,"figure":"https://media.prts.wiki/9/9b/Avg_avgnew_275_breeze_1-6$1.png"},{"type":"dialog","id":104},{"type":"delay","time":"0.7","id":105},{"type":"playsound","key":"$rungeneral","volume":"1","id":106},{"type":"move","name":"middle","xpos":"-300","fadetime":"2","block":"false","id":107},{"type":"character","fadetime":"0.5","id":108},{"type":"delay","time":"2","id":109},{"type":"playsound","key":"$d_avg_clothmovement","volume":"1","id":110},{"type":"delay","time":"0.5","id":111},{"type":"playsound","key":"$leaveshake","volume":"0.5","id":112},{"type":"delay","time":"2","id":113},{"type":"character","name":"avg_npc_243","id":114},{"type":"delay","time":"0.5","id":115},{"type":"move","name":"middle","xpos":"-50","fadetime":"1","block":"false","id":116},{"type":"camerashake","duration":"0.3","xstrength":"30","ystrength":"30","vibrato":"30","randomness":"90","fadeout":"true","block":"false","id":117},{"type":"dialogue","name":"女仆","text":"小姐——！","id":118,"figure":"https://media.prts.wiki/5/5e/Avg_avg_npc_243.png"},{"type":"dialog","id":119},{"type":"delay","time":"1","id":120},{"type":"blocker","a":"0","r":"0","g":"0","b":"0","fadetime":"0","block":"true","id":121},{"type":"blocker","a":"1","r":"0","g":"0","b":"0","fadetime":"2","block":"true","id":122},{"type":"character","id":123},{"type":"background","image":"https://media.prts.wiki/7/70/Avg_bg_bg_forest.png","screenadapt":"showall","id":124},{"type":"delay","time":"2","id":125},{"type":"playmusic","intro":"$path_intro","key":"https://static.prts.wiki/music/music/a001/m_dia_path_loop.mp3","volume":"0.4","id":126,"musicid":1},{"type":"blocker","a":"0","r":"0","g":"0","b":"0","fadetime":"2","block":"true","id":127},{"type":"delay","time":"2","text":"","id":128},{"type":"text","text":"07:51 A.M.","id":129},{"type":"text","text":"多伦郡，岩溪镇外，临时安置点","id":130},{"type":"text","text":"镇外森林，文明与荒蛮交织的地方，一群失魂落魄的人被丢弃、堆放在此，潦倒地沉默着。","id":131},{"type":"text","text":"湿冷的晨雾渐渐消去，一道道阳光照入深灰色的树林。","id":132},{"type":"dialog","id":133},{"type":"playsound","key":"$leaveshake","volume":"1","id":134},{"type":"character","name":"avgnew_275_breeze_1#1$1","fadetime":"1.5","id":135},{"type":"delay","time":"2","text":"","id":136},{"type":"character","name":"avgnew_275_breeze_1#6$1","id":137},{"type":"dialogue","name":"格蕾丝","text":"大伙儿！我回来了！","id":138,"figure":"https://media.prts.wiki/9/9b/Avg_avgnew_275_breeze_1-6$1.png"},{"type":"character","name":"avg_npc_005","id":139},{"type":"dialogue","name":"聒噪的老人","text":"天哪，又是你。你又要来折腾什么事了？好像这个地方还不够乱似的。","id":140,"figure":"https://media.prts.wiki/d/d5/Avg_avg_npc_005.png"},{"type":"character","name":"avgnew_275_breeze_1#1$1","id":141},{"type":"dialogue","name":"格蕾丝","text":"还记得我上次跟你们要的个人信息吗？","id":142,"figure":"https://media.prts.wiki/3/3a/Avg_avgnew_275_breeze_1-1$1.png"},{"type":"character","name":"avg_npc_005","id":143},{"type":"dialogue","name":"聒噪的老人","text":"具体地说是“四天前”，这期间我们都没再看到过你。","id":144,"figure":"https://media.prts.wiki/d/d5/Avg_avg_npc_005.png"},{"type":"character","name":"avgnew_275_breeze_1#4$1","id":145},{"type":"dialogue","name":"格蕾丝","text":"不，我没有及时回复你们是因为——","id":146,"figure":"https://media.prts.wiki/0/0d/Avg_avgnew_275_breeze_1-4$1.png"},{"type":"character","name":"avg_npc_005","id":147},{"type":"dialogue","name":"聒噪的老人","text":"因为我们没能达成交易，不是吗？你想要玛丽安的情报，你觉得我们有所隐瞒，你吊着我们，现在来看看我们是否会松口。","id":148,"figure":"https://media.prts.wiki/d/d5/Avg_avg_npc_005.png"},{"type":"character","name":"avg_npc_242","id":149},{"type":"dialogue","name":"彬彬有礼的先生","text":"冷静下来，朋友。她不是你的工头，看看她，只是一个小女孩，她没有这样的套路。","id":150,"figure":"https://media.prts.wiki/7/7c/Avg_avg_npc_242.png"},{"type":"character","name":"avg_npc_005","id":151},{"type":"dialogue","name":"聒噪的老人","text":"表象总有迷惑性，谁知道她隐藏了什么身份。","id":152,"figure":"https://media.prts.wiki/d/d5/Avg_avg_npc_005.png"},{"type":"character","name":"avg_npc_242","id":153},{"type":"dialogue","name":"彬彬有礼的先生","text":"小沃尔珀，你确实得给我们解释一下个人信息的事情。","id":154,"figure":"https://media.prts.wiki/7/7c/Avg_avg_npc_242.png"},{"type":"character","name":"avgnew_275_breeze_1#4$1","id":155},{"type":"dialogue","name":"格蕾丝","text":"正如我之前所说的，我请求了很多医生，只有一位没当面拒绝我......","id":156,"figure":"https://media.prts.wiki/0/0d/Avg_avgnew_275_breeze_1-4$1.png"},{"type":"dialogue","name":"格蕾丝","text":"他要求我先过来收集你们的个人信息，了解一下你们的身体状况，然后他就会来帮你们。","id":157,"figure":"https://media.prts.wiki/0/0d/Avg_avgnew_275_breeze_1-4$1.png"},{"type":"dialogue","name":"格蕾丝","text":"抱歉，不知道为什么，之前拿着整理完的资料过去时，医生正好不在。这几天他一直都不在......","id":158,"figure":"https://media.prts.wiki/0/0d/Avg_avgnew_275_breeze_1-4$1.png"},{"type":"character","name":"avg_npc_005","id":159},{"type":"dialogue","name":"聒噪的老人","text":"这么巧啊！","id":160,"figure":"https://media.prts.wiki/d/d5/Avg_avg_npc_005.png"},{"type":"character","name":"avg_npc_242","id":161},{"type":"dialogue","name":"彬彬有礼的先生","text":"让她说下去。","id":162,"figure":"https://media.prts.wiki/7/7c/Avg_avg_npc_242.png"},{"type":"character","name":"avgnew_275_breeze_1#4$1","id":163},{"type":"dialogue","name":"格蕾丝","text":"......这期间我也只能一边等着，一边寻找其他途径。","id":164,"figure":"https://media.prts.wiki/0/0d/Avg_avgnew_275_breeze_1-4$1.png"},{"type":"character","name":"avgnew_275_breeze_1#1$1","id":165},{"type":"dialogue","name":"格蕾丝","text":"我在他诊所的门上装了发信器，只要他开门我就会收到信号！看这个红灯，从今天清晨就在闪了！","id":166,"figure":"https://media.prts.wiki/3/3a/Avg_avgnew_275_breeze_1-1$1.png"},{"type":"character","name":"avg_npc_242","id":167},{"type":"dialogue","name":"彬彬有礼的先生","text":"那你还不去找他，在这里做什么？","id":168,"figure":"https://media.prts.wiki/7/7c/Avg_avg_npc_242.png"},{"type":"character","name":"avgnew_275_breeze_1#4$1","id":169},{"type":"dialogue","name":"格蕾丝","text":"我想先更新一下身体状况信息。如果是四天前的报告，医生可能会产生误判......？我也不是很懂，我想这样更稳妥些。","id":170,"figure":"https://media.prts.wiki/0/0d/Avg_avgnew_275_breeze_1-4$1.png"},{"type":"character","name":"avg_npc_005","id":171},{"type":"dialogue","name":"聒噪的老人","text":"你当初来只是为了打听玛丽安的消息，并不是真的想来帮我们。我们为什么要相信你？","id":172,"figure":"https://media.prts.wiki/d/d5/Avg_avg_npc_005.png"},{"type":"character","name":"avgnew_275_breeze_1#2$1","id":173},{"type":"dialogue","name":"格蕾丝","text":"我——","id":174,"figure":"https://media.prts.wiki/e/ed/Avg_avgnew_275_breeze_1-2$1.png"},{"type":"character","name":"avg_npc_242","id":175},{"type":"dialogue","name":"彬彬有礼的先生","text":"你用不着跟他解释，他还总是幻想那些贵族会跑来救我们呢。","id":176,"figure":"https://media.prts.wiki/7/7c/Avg_avg_npc_242.png"},{"type":"character","name":"avg_npc_005","id":177},{"type":"camerashake","duration":"0.3","xstrength":"30","ystrength":"30","vibrato":"30","randomness":"90","fadeout":"true","block":"false","id":178},{"type":"dialogue","name":"聒噪的老人","text":"呸！他们一定会的，只是现在还不知道我们的情况罢了。","id":179,"figure":"https://media.prts.wiki/d/d5/Avg_avg_npc_005.png"},{"type":"character","name":"avg_npc_242","id":180},{"type":"dialogue","name":"彬彬有礼的先生","text":"小姑娘，玛丽安确实已经失踪很久了。你在我们身上投入再多精力，我们也不可能把她凭空给你变出来。","id":181,"figure":"https://media.prts.wiki/7/7c/Avg_avg_npc_242.png"},{"type":"character","name":"avgnew_275_breeze_1#4$1","id":182},{"type":"dialogue","name":"格蕾丝","text":"我知道，我对她还比较放心，专注当下的事情更重要。","id":183,"figure":"https://media.prts.wiki/0/0d/Avg_avgnew_275_breeze_1-4$1.png"},{"type":"character","name":"avg_npc_242","id":184},{"type":"dialogue","name":"彬彬有礼的先生","text":"她也只是个和你差不多大的小孩，森林里什么都说不好。","id":185,"figure":"https://media.prts.wiki/7/7c/Avg_avg_npc_242.png"},{"type":"character","name":"avgnew_275_breeze_1#1$1","id":186},{"type":"dialogue","name":"格蕾丝","text":"还没搬来这里时我就认识她，我经常溜出去找她玩。她可喜欢植物了。森林里那么多植物，她至少不会饿肚子。","id":187,"figure":"https://media.prts.wiki/3/3a/Avg_avgnew_275_breeze_1-1$1.png"},{"type":"dialogue","name":"格蕾丝","text":"而且她最早给我发的求援信，就是让我帮助你们所有人。我得把你们照顾好，这样我和她重逢的时候就不会被她念叨啦。","id":188,"figure":"https://media.prts.wiki/3/3a/Avg_avgnew_275_breeze_1-1$1.png"},{"type":"character","name":"avg_npc_242","id":189},{"type":"dialogue","name":"彬彬有礼的先生","text":"不论他们说什么，我会站在你这边。要是他们不愿意，我会陪你去说服他们。","id":190,"figure":"https://media.prts.wiki/7/7c/Avg_avg_npc_242.png"},{"type":"character","name":"avgnew_275_breeze_1#6$1","id":191},{"type":"dialogue","name":"格蕾丝","text":"谢谢。","id":192,"figure":"https://media.prts.wiki/9/9b/Avg_avgnew_275_breeze_1-6$1.png"},{"type":"character","name":"avg_npc_242","id":193},{"type":"dialogue","name":"彬彬有礼的先生","text":"不如从我先开始登记？忙完这里的事后，我得去砍些更大的木头。","id":194,"figure":"https://media.prts.wiki/7/7c/Avg_avg_npc_242.png"},{"type":"character","name":"avgnew_275_breeze_1#1$1","id":195},{"type":"dialogue","name":"格蕾丝","text":"你要用来干什么？","id":196,"figure":"https://media.prts.wiki/3/3a/Avg_avgnew_275_breeze_1-1$1.png"},{"type":"character","name":"avg_npc_242","id":197},{"type":"dialogue","name":"彬彬有礼的先生","text":"我们打算造一个大点的木屋，这样大家都能住进去。一切都会好起来的。","id":198,"figure":"https://media.prts.wiki/7/7c/Avg_avg_npc_242.png"},{"type":"character","name":"avgnew_275_breeze_1#1$1","id":199},{"type":"dialogue","name":"格蕾丝","text":"是的，一定都会好起来的。","id":200,"figure":"https://media.prts.wiki/3/3a/Avg_avgnew_275_breeze_1-1$1.png"},{"type":"dialog","id":201},{"type":"blocker","a":"0","r":"0","g":"0","b":"0","fadetime":"0","block":"true","id":202},{"type":"blocker","a":"1","r":"0","g":"0","b":"0","fadetime":"2","block":"true","id":203},{"type":"character","id":204},{"type":"background","image":"https://media.prts.wiki/6/64/Avg_bg_29_g3_cottage.png","screenadapt":"showall","id":205},{"type":"delay","time":"2","id":206},{"type":"blocker","a":"0","r":"0","g":"0","b":"0","fadetime":"2","block":"true","id":207},{"type":"delay","time":"2","text":"","id":208},{"type":"text","text":"01:32 P.M.","id":209},{"type":"text","text":"多伦郡，岩溪镇，邵家诊所","id":210},{"type":"text","text":"被安置在整洁的街角外墙内的是一间老旧办公室。格蕾丝四天前来过这里。经过四天的时光，一些角落的灰尘更厚了。","id":211},{"type":"text","text":"办公室的窗户被厚厚的污渍覆盖着。这间办公室原本面朝整个小镇，如今，工业的音符也一同汇流到了西边的这几扇窗上。","id":212},{"type":"text","text":"一个瘦小的男人坐在桌前，低头咕哝着。那是来自其他国度的语言，偶尔夹杂着一些维多利亚语。","id":213},{"type":"character","name":"avg_npc_033","id":214},{"type":"multiline","name":"医生","text":"账单......","id":215},{"type":"character","name":"avg_npc_033","id":216},{"type":"multiline","name":"医生","text":"账单......","id":217},{"type":"character","name":"avg_npc_033","id":218},{"type":"camerashake","duration":"0.3","xstrength":"30","ystrength":"30","vibrato":"30","randomness":"90","fadeout":"true","block":"false","id":219},{"type":"multiline","name":"医生","text":"*维多利亚粗口*！","id":220},{"type":"dialog","id":221},{"type":"dialog","id":222},{"type":"dialog","id":223},{"type":"character","id":224},{"type":"playsound","key":"$doorknockquite","volume":"0.7","id":225},{"type":"delay","time":"0.5","id":226},{"type":"dialogue","name":"？？？","text":"咳咳——","id":227},{"type":"character","name":"avg_npc_033","id":228},{"type":"dialogue","name":"医生","text":"今天预约满了。","id":229,"figure":"https://media.prts.wiki/4/46/Avg_avg_npc_033.png"},{"type":"dialog","id":230},{"type":"character","id":231},{"type":"dialogue","name":"？？？","text":"说好的东西，我拿来了。","id":232},{"type":"dialog","id":233},{"type":"character","id":234},{"type":"playsound","key":"$d_gen_walk_n","id":235},{"type":"character","name":"avgnew_275_breeze_1#1$1","fadetime":"1.5","id":236},{"type":"delay","time":"2","id":237},{"type":"text","text":"医生猛地抬起头回望声音传来的方向，阳光被朝东的窗塑造成一个又一个的梯形投影。","id":238},{"type":"text","text":"一个金发的沃尔珀就站在他办公室的门口，她的发梢被阳光轻轻挽起，显得熠熠生辉。","id":239},{"type":"character","name":"avg_npc_033","name2":"avgnew_275_breeze_1#1$1","focus":"1","id":240},{"type":"dialogue","name":"医生","text":"是你......？！","id":241,"figure":"https://media.prts.wiki/4/46/Avg_avg_npc_033.png"},{"type":"character","name":"avg_npc_033","name2":"avgnew_275_breeze_1#1$1","focus":"2","id":242},{"type":"dialogue","name":"格蕾丝","text":"给您，都整理好装订起来了。","id":243,"figure":"https://media.prts.wiki/3/3a/Avg_avgnew_275_breeze_1-1$1.png"},{"type":"dialog","id":244},{"type":"playsound","key":"$d_avg_clothmovement","volume":"1","id":245},{"type":"move","name":"right","xpos":"-10","fadetime":"1","isblock":"true","id":246},{"type":"move","name":"right","xpos":"10","fadetime":"1","isblock":"true","id":247},{"type":"character","name":"avg_npc_033","name2":"avgnew_275_breeze_1#1$1","id":248},{"type":"playsound","key":"$d_avg_paper1","id":249},{"type":"delay","time":"1.5","id":250},{"type":"character","name":"avg_npc_033","name2":"avgnew_275_breeze_1#1$1","focus":"1","id":251},{"type":"dialogue","name":"医生","text":"......你真的去做了。","id":252,"figure":"https://media.prts.wiki/4/46/Avg_avg_npc_033.png"},{"type":"dialog","id":253},{"type":"character","name":"avg_npc_033","name2":"avgnew_275_breeze_1#1$1","id":254},{"type":"playsound","key":"$d_avg_paper1","id":255},{"type":"delay","time":"1.5","id":256},{"type":"character","name":"avg_npc_033","name2":"avgnew_275_breeze_1#1$1","focus":"1","id":257},{"type":"dialogue","name":"医生","text":"这些健康报告，你是怎么做到的？你还只是一个孩子。","id":258,"figure":"https://media.prts.wiki/4/46/Avg_avg_npc_033.png"},{"type":"character","name":"avg_npc_033","name2":"avgnew_275_breeze_1#1$1","focus":"2","id":259},{"type":"dialogue","name":"格蕾丝","text":"我家里有一些医学方面的书，被禁足的时候，我就会翻着看看。","id":260,"figure":"https://media.prts.wiki/3/3a/Avg_avgnew_275_breeze_1-1$1.png"},{"type":"character","name":"avg_npc_033","name2":"avgnew_275_breeze_1#6$1","focus":"2","id":261},{"type":"dialogue","name":"格蕾丝","text":"应该有挺多错误的，仅供参考啦。","id":262,"figure":"https://media.prts.wiki/9/9b/Avg_avgnew_275_breeze_1-6$1.png"},{"type":"dialog","id":263},{"type":"character","name":"avg_npc_033","name2":"avgnew_275_breeze_1#6$1","id":264},{"type":"playsound","key":"$d_avg_paper1","id":265},{"type":"delay","time":"1.5","id":266},{"type":"character","name":"avg_npc_033","name2":"avgnew_275_breeze_1#6$1","focus":"1","id":267},{"type":"dialogue","name":"医生","text":"......好，很好......你做得真的很好......","id":268,"figure":"https://media.prts.wiki/4/46/Avg_avg_npc_033.png"},{"type":"character","name":"avg_npc_033","name2":"avgnew_275_breeze_1#1$1","focus":"2","id":269},{"type":"dialogue","name":"格蕾丝","text":"现在该轮到您了。","id":270,"figure":"https://media.prts.wiki/3/3a/Avg_avgnew_275_breeze_1-1$1.png"},{"type":"character","name":"avg_npc_033","name2":"avgnew_275_breeze_1#1$1","focus":"1","id":271},{"type":"dialogue","name":"医生","text":"关于这个......","id":272,"figure":"https://media.prts.wiki/4/46/Avg_avg_npc_033.png"},{"type":"dialog","id":273},{"type":"delay","time":"1.5","id":274},{"type":"character","name":"avg_npc_033","name2":"avgnew_275_breeze_1#1$1","focus":"1","id":275},{"type":"delay","time":"1.5","id":276},{"type":"character","name":"avg_npc_033","name2":"avgnew_275_breeze_1#1$1","focus":"1","id":277},{"type":"dialogue","name":"医生","text":"我今天要去佩勒姆家一趟，可以等回来以后再给你回复吗？","id":278,"figure":"https://media.prts.wiki/4/46/Avg_avg_npc_033.png"},{"type":"dialog","id":279},{"type":"stopmusic","id":280},{"type":"character","name":"avg_npc_033","name2":"avgnew_275_breeze_1#2$1","id":281},{"type":"jump","name":"right","power":"3","times":"1","fadetime":"0.5","isblock":"false","id":282},{"type":"delay","time":"1","id":283},{"type":"text","text":"佩勒姆——这个名字像电击一般击中了格蕾丝。","id":284},{"type":"text","text":"一个不详的信号。","id":285},{"type":"playmusic","intro":"$dignified_intro","key":"https://static.prts.wiki/music/music/act9d0d0/m_avg_dignified_loop.mp3","volume":"0.4","id":286,"musicid":2},{"type":"character","name":"avg_npc_033","name2":"avgnew_275_breeze_1#4$1","focus":"2","id":287},{"type":"dialogue","name":"格蕾丝","text":"为什么？","id":288,"figure":"https://media.prts.wiki/0/0d/Avg_avgnew_275_breeze_1-4$1.png"},{"type":"character","name":"avg_npc_033","name2":"avgnew_275_breeze_1#4$1","focus":"1","id":289},{"type":"dialogue","name":"医生","text":"我的客户通常都是要求上门服务的。","id":290,"figure":"https://media.prts.wiki/4/46/Avg_avg_npc_033.png"},{"type":"character","name":"avg_npc_033","name2":"avgnew_275_breeze_1#5$1","focus":"2","id":291},{"type":"dialogue","name":"格蕾丝","text":"我是说，我不理解为什么非要去过她家后才能答复。","id":292,"figure":"https://media.prts.wiki/0/07/Avg_avgnew_275_breeze_1-5$1.png"},{"type":"character","name":"avg_npc_033","name2":"avgnew_275_breeze_1#5$1","focus":"1","id":293},{"type":"dialogue","name":"医生","text":"......","id":294,"figure":"https://media.prts.wiki/4/46/Avg_avg_npc_033.png"},{"type":"character","name":"avg_npc_033","name2":"avgnew_275_breeze_1#5$1","focus":"2","id":295},{"type":"dialogue","name":"格蕾丝","text":"所以......一切又回到她身上了？","id":296,"figure":"https://media.prts.wiki/0/07/Avg_avgnew_275_breeze_1-5$1.png"},{"type":"dialogue","name":"格蕾丝","text":"您不是她的私人医生，而她平时都住在移动城市，每年只有一个月会来这里亲自监督工厂运作，为什么人人都要看她的脸色？","id":297,"figure":"https://media.prts.wiki/0/07/Avg_avgnew_275_breeze_1-5$1.png"},{"type":"character","name":"avg_npc_033","name2":"avgnew_275_breeze_1#5$1","focus":"1","id":298},{"type":"dialogue","name":"医生","text":"唉，事情没有那么简单......","id":299,"figure":"https://media.prts.wiki/4/46/Avg_avg_npc_033.png"},{"type":"character","name":"avg_npc_033","name2":"avgnew_275_breeze_1#5$1","focus":"2","id":300},{"type":"dialogue","name":"格蕾丝","text":"在我看来，您和其他人一样，都被她控制了。","id":301,"figure":"https://media.prts.wiki/0/07/Avg_avgnew_275_breeze_1-5$1.png"},{"type":"character","name":"avg_npc_033","name2":"avgnew_275_breeze_1#5$1","focus":"1","id":302},{"type":"dialogue","name":"医生","text":"她没有控制我。","id":303,"figure":"https://media.prts.wiki/4/46/Avg_avg_npc_033.png"},{"type":"character","name":"avg_npc_033","name2":"avgnew_275_breeze_1#5$1","focus":"2","id":304},{"type":"dialogue","name":"格蕾丝","text":"但如果有她的支持，事情会变得容易一些不是吗？","id":305,"figure":"https://media.prts.wiki/0/07/Avg_avgnew_275_breeze_1-5$1.png"},{"type":"character","name":"avg_npc_033","name2":"avgnew_275_breeze_1#5$1","focus":"1","id":306},{"type":"dialogue","name":"医生","text":"......","id":307,"figure":"https://media.prts.wiki/4/46/Avg_avg_npc_033.png"},{"type":"dialogue","name":"医生","text":"听着，小孩。","id":308,"figure":"https://media.prts.wiki/4/46/Avg_avg_npc_033.png"},{"type":"dialogue","name":"医生","text":"他们把我当成奢侈品，一种潮流，一种生活方式，一种附加值。我的工作与家庭都建立在这个基础之上，如今我已经难以抽身......","id":309,"figure":"https://media.prts.wiki/4/46/Avg_avg_npc_033.png"},{"type":"dialogue","name":"医生","text":"我的房租，我孩子的学费，我妻子治疗矿石病的钱......我不能丢了我现在的工作。","id":310,"figure":"https://media.prts.wiki/4/46/Avg_avg_npc_033.png"},{"type":"dialogue","name":"医生","text":"这不是一个打败什么人就能让事情变好的童话故事。真正的敌人是无形的，它是“活着”的副产品，它是生活本身。","id":311,"figure":"https://media.prts.wiki/4/46/Avg_avg_npc_033.png"},{"type":"character","name":"avg_npc_033","name2":"avgnew_275_breeze_1#4$1","focus":"2","id":312},{"type":"dialogue","name":"格蕾丝","text":"......","id":313,"figure":"https://media.prts.wiki/0/0d/Avg_avgnew_275_breeze_1-4$1.png"},{"type":"dialogue","name":"格蕾丝","text":"可救助这些人怎么就触及贵族们的利益了？","id":314,"figure":"https://media.prts.wiki/0/0d/Avg_avgnew_275_breeze_1-4$1.png"},{"type":"character","name":"avg_npc_033","name2":"avgnew_275_breeze_1#4$1","focus":"1","id":315},{"type":"dialogue","name":"医生","text":"我没法站在佩勒姆夫人的位置，我看不到事情的全貌。","id":316,"figure":"https://media.prts.wiki/4/46/Avg_avg_npc_033.png"},{"type":"character","name":"avg_npc_033","name2":"avgnew_275_breeze_1#4$1","focus":"2","id":317},{"type":"dialogue","name":"格蕾丝","text":"他们只是一些人畜无害的可怜人啊。","id":318,"figure":"https://media.prts.wiki/0/0d/Avg_avgnew_275_breeze_1-4$1.png"},{"type":"character","name":"avg_npc_033","name2":"avgnew_275_breeze_1#4$1","focus":"1","id":319},{"type":"dialogue","name":"医生","text":"若他们不是那么无关宏旨，你觉得他们还会有这种待遇吗？","id":320,"figure":"https://media.prts.wiki/4/46/Avg_avg_npc_033.png"},{"type":"dialogue","name":"医生","text":"至于其他贵族，我想没人会得罪一个嫁给佩勒姆家族的、开了多家工厂的，报社老板的女儿。","id":321,"figure":"https://media.prts.wiki/4/46/Avg_avg_npc_033.png"},{"type":"character","name":"avg_npc_033","name2":"avgnew_275_breeze_1#4$1","focus":"2","id":322},{"type":"dialogue","name":"格蕾丝","text":"邵先生，我的自由时间快耗尽了。今天还能够出来纯属意外，我是想抓住这次“意外”，以及您给我的希望，再最后努力一把......","id":323,"figure":"https://media.prts.wiki/0/0d/Avg_avgnew_275_breeze_1-4$1.png"},{"type":"character","name":"avg_npc_033","name2":"avgnew_275_breeze_1#5$1","focus":"2","id":324},{"type":"dialogue","name":"格蕾丝","text":"如果我做得还不够，您可以告诉我，我会继续去做。","id":325,"figure":"https://media.prts.wiki/0/07/Avg_avgnew_275_breeze_1-5$1.png"},{"type":"character","name":"avg_npc_033","name2":"avgnew_275_breeze_1#5$1","focus":"1","id":326},{"type":"dialogue","name":"医生","text":"这段时间你在做什么呢？","id":327,"figure":"https://media.prts.wiki/4/46/Avg_avg_npc_033.png"},{"type":"character","name":"avg_npc_033","name2":"avgnew_275_breeze_1#5$1","focus":"2","id":328},{"type":"dialogue","name":"格蕾丝","text":"我请求了各种各样的人。","id":329,"figure":"https://media.prts.wiki/0/07/Avg_avgnew_275_breeze_1-5$1.png"},{"type":"character","name":"avg_npc_033","name2":"avgnew_275_breeze_1#5$1","focus":"1","id":330},{"type":"dialogue","name":"医生","text":"所以你基本上就是把自己的希望寄托在别人身上。","id":331,"figure":"https://media.prts.wiki/4/46/Avg_avg_npc_033.png"},{"type":"character","name":"avg_npc_033","name2":"avgnew_275_breeze_1#4$1","focus":"2","id":332},{"type":"dialogue","name":"格蕾丝","text":"......","id":333,"figure":"https://media.prts.wiki/0/0d/Avg_avgnew_275_breeze_1-4$1.png"},{"type":"dialogue","name":"格蕾丝","text":"......您说得没错......","id":334,"figure":"https://media.prts.wiki/0/0d/Avg_avgnew_275_breeze_1-4$1.png"},{"type":"character","name":"avg_npc_033","name2":"avgnew_275_breeze_1#4$1","focus":"1","id":335},{"type":"dialogue","name":"医生","text":"我没资格去对你说什么，但是——","id":336,"figure":"https://media.prts.wiki/4/46/Avg_avg_npc_033.png"},{"type":"dialogue","name":"医生","text":"我很羡慕你，你有能力，你还纯真，你的动机简单，你稚气未脱、活力四射、满腔热血，生活还没有朝你扣动扳机。","id":337,"figure":"https://media.prts.wiki/4/46/Avg_avg_npc_033.png"},{"type":"dialogue","name":"医生","text":"但你为什么不亲自去做？你在担忧什么？","id":338,"figure":"https://media.prts.wiki/4/46/Avg_avg_npc_033.png"},{"type":"character","name":"avg_npc_033","name2":"avgnew_275_breeze_1#4$1","focus":"2","id":339},{"type":"dialogue","name":"格蕾丝","text":"......我......","id":340,"figure":"https://media.prts.wiki/0/0d/Avg_avgnew_275_breeze_1-4$1.png"},{"type":"dialogue","name":"格蕾丝","text":"我的家人可能会不满，或者佩勒姆家族会不满，或者镇子里的人会......","id":341,"figure":"https://media.prts.wiki/0/0d/Avg_avgnew_275_breeze_1-4$1.png"},{"type":"character","name":"avg_npc_033","name2":"avgnew_275_breeze_1#4$1","focus":"1","id":342},{"type":"dialogue","name":"医生","text":"等等等等，你只是一个普普通通的小孩，你不该被那么多复杂的东西束缚着，别这么思考问题。","id":343,"figure":"https://media.prts.wiki/4/46/Avg_avg_npc_033.png"},{"type":"dialogue","name":"医生","text":"听着......","id":344,"figure":"https://media.prts.wiki/4/46/Avg_avg_npc_033.png"},{"type":"dialogue","name":"医生","text":"与你约定的当晚，我就写信去找她说起过这件事。她暗示我，一件奢侈品的价值成分是复杂的......","id":345,"figure":"https://media.prts.wiki/4/46/Avg_avg_npc_033.png"},{"type":"dialogue","name":"医生","text":"如果厂商决定把自己的奢侈品免费送给穷人，那奢侈品就将一文不值。","id":346,"figure":"https://media.prts.wiki/4/46/Avg_avg_npc_033.png"},{"type":"dialogue","name":"医生","text":"她要我看清自己的“消费人群”。","id":347,"figure":"https://media.prts.wiki/4/46/Avg_avg_npc_033.png"},{"type":"character","name":"avg_npc_033","name2":"avgnew_275_breeze_1#4$1","focus":"2","id":348},{"type":"dialogue","name":"格蕾丝","text":"她在威胁您。","id":349,"figure":"https://media.prts.wiki/0/0d/Avg_avgnew_275_breeze_1-4$1.png"},{"type":"character","name":"avg_npc_033","name2":"avgnew_275_breeze_1#4$1","focus":"1","id":350},{"type":"dialogue","name":"医生","text":"这不是威胁，这是提醒。她没必要威胁我，就算我突然决定变成一个混账，也不会对她产生任何影响的。","id":351,"figure":"https://media.prts.wiki/4/46/Avg_avg_npc_033.png"},{"type":"dialogue","name":"医生","text":"......我觉得我现在已经是了......","id":352,"figure":"https://media.prts.wiki/4/46/Avg_avg_npc_033.png"},{"type":"dialogue","name":"医生","text":"我曾经给了你错误的希望，如今我还是要和你说清楚......","id":353,"figure":"https://media.prts.wiki/4/46/Avg_avg_npc_033.png"},{"type":"dialogue","name":"医生","text":"......","id":354,"figure":"https://media.prts.wiki/4/46/Avg_avg_npc_033.png"},{"type":"dialogue","name":"医生","text":"孩子，很惭愧地告诉你。最初与你达成这样的约定，是因为我从来不认为像你这种小屁孩会真的去帮助他们。","id":355,"figure":"https://media.prts.wiki/4/46/Avg_avg_npc_033.png"},{"type":"character","name":"avg_npc_033","name2":"avgnew_275_breeze_1#4$1","focus":"2","id":356},{"type":"dialogue","name":"格蕾丝","text":"所以您从一开始就是想拒绝我的，只是不好意思直接开口？","id":357,"figure":"https://media.prts.wiki/0/0d/Avg_avgnew_275_breeze_1-4$1.png"},{"type":"character","name":"avg_npc_033","name2":"avgnew_275_breeze_1#4$1","focus":"1","id":358},{"type":"dialogue","name":"医生","text":"抱歉，让你产生了虚假的希望。","id":359,"figure":"https://media.prts.wiki/4/46/Avg_avg_npc_033.png"},{"type":"character","name":"avg_npc_033","name2":"avgnew_275_breeze_1#4$1","focus":"2","id":360},{"type":"dialogue","name":"格蕾丝","text":"......我......","id":361,"figure":"https://media.prts.wiki/0/0d/Avg_avgnew_275_breeze_1-4$1.png"},{"type":"dialog","id":362},{"type":"character","name":"avg_npc_033","name2":"avgnew_275_breeze_1#5$1","focus":"2","id":363},{"type":"move","name":"right","xpos":"-10","fadetime":"0.5","isblock":"true","id":364},{"type":"dialogue","name":"格蕾丝","text":"您知道亚利桑那家吗？亚利桑那家的大小姐是我的朋友，如果我拜托她来求您帮忙，您会同意吗？","id":365,"figure":"https://media.prts.wiki/0/07/Avg_avgnew_275_breeze_1-5$1.png"},{"type":"character","name":"avg_npc_033","name2":"avgnew_275_breeze_1#5$1","focus":"1","id":366},{"type":"dialogue","name":"医生","text":"你有一个贵族朋友，那你就更不该把贵族想得那么简单了。","id":367,"figure":"https://media.prts.wiki/4/46/Avg_avg_npc_033.png"},{"type":"dialogue","name":"医生","text":"这件事，与亚利桑那没有直接的利益冲突，他们没必要主动站到佩勒姆的对面。","id":368,"figure":"https://media.prts.wiki/4/46/Avg_avg_npc_033.png"},{"type":"character","name":"avg_npc_033","name2":"avgnew_275_breeze_1#5$1","focus":"2","id":369},{"type":"dialogue","name":"格蕾丝","text":"可那些人在逐渐死去，他们总不会不管吧？那些荣耀呢？","id":370,"figure":"https://media.prts.wiki/0/07/Avg_avgnew_275_breeze_1-5$1.png"},{"type":"character","name":"avg_npc_033","name2":"avgnew_275_breeze_1#5$1","focus":"1","id":371},{"type":"dialogue","name":"医生","text":"贵族之所以是贵族，主要依靠的是认同感。这种认同感不必来自庶民，但必须来自其他贵族。","id":372,"figure":"https://media.prts.wiki/4/46/Avg_avg_npc_033.png"},{"type":"dialogue","name":"医生","text":"至于荣耀，那只是依附于权力与金钱之上的装饰罢了。","id":373,"figure":"https://media.prts.wiki/4/46/Avg_avg_npc_033.png"},{"type":"character","name":"avg_npc_033","name2":"avgnew_275_breeze_1#5$1","focus":"2","id":374},{"type":"dialogue","name":"格蕾丝","text":"万一亚利桑那家不是通常的贵族呢？我和他们家的大小姐玩得很好，我知道他们是不一样的！","id":375,"figure":"https://media.prts.wiki/0/07/Avg_avgnew_275_breeze_1-5$1.png"},{"type":"character","name":"avg_npc_033","name2":"avgnew_275_breeze_1#5$1","focus":"1","id":376},{"type":"dialogue","name":"医生","text":"面对现实吧，他们是一样的。","id":377,"figure":"https://media.prts.wiki/4/46/Avg_avg_npc_033.png"},{"type":"dialogue","name":"医生","text":"你知道亚利桑那夫人和男爵并不是真心相爱吗？","id":378,"figure":"https://media.prts.wiki/4/46/Avg_avg_npc_033.png"},{"type":"dialogue","name":"医生","text":"他们就是那种最常见的，基于利益交换的婚姻。一方提供身份，一方则提供源石技艺的威慑力。","id":379,"figure":"https://media.prts.wiki/4/46/Avg_avg_npc_033.png"},{"type":"dialogue","name":"医生","text":"我不认为他们与其他贵族有什么差别。非要说的话，他们还在挣扎，这反而会使他们更加保守。","id":380,"figure":"https://media.prts.wiki/4/46/Avg_avg_npc_033.png"},{"type":"character","name":"avg_npc_033","name2":"avgnew_275_breeze_1#5$1","focus":"2","id":381},{"type":"dialogue","name":"格蕾丝","text":"您说我的......","id":382,"figure":"https://media.prts.wiki/0/07/Avg_avgnew_275_breeze_1-5$1.png"},{"type":"dialog","id":383},{"type":"move","name":"right","xpos":"10","fadetime":"0.5","isblock":"true","id":384},{"type":"character","name":"avg_npc_033","name2":"avgnew_275_breeze_1#4$1","focus":"2","id":385},{"type":"delay","time":"1.5","id":386},{"type":"character","name":"avg_npc_033","name2":"avgnew_275_breeze_1#4$1","focus":"2","id":387},{"type":"dialogue","name":"格蕾丝","text":"您说那对亚利桑那夫妇是......","id":388,"figure":"https://media.prts.wiki/0/0d/Avg_avgnew_275_breeze_1-4$1.png"},{"type":"dialog","id":389},{"type":"delay","time":"2.5","id":390},{"type":"character","id":391},{"type":"text","text":"她没法继续说下去。句子的结构与逻辑，伴随着她内心深处的一些东西开始逐渐崩裂......","id":392},{"type":"text","text":"正如康塞尔为她造过的无数雪城堡，痛苦地迎来下一个季节。","id":393},{"type":"text","text":"融化后的雪水在她眼眶里打转。","id":394},{"type":"character","name":"avg_npc_033","name2":"avgnew_275_breeze_1#4$1","focus":"1","id":395},{"type":"dialogue","name":"医生","text":"时间不早了，我得赶紧去完成佩勒姆家的工作，然后去城里处理一下我儿子在学校里造成的破坏......","id":396,"figure":"https://media.prts.wiki/4/46/Avg_avg_npc_033.png"},{"type":"dialogue","name":"医生","text":"如果有什么消息，我会写信告诉你的。","id":397,"figure":"https://media.prts.wiki/4/46/Avg_avg_npc_033.png"},{"type":"dialogue","name":"医生","text":"再次向你致歉，虽然你还小......你是一个值得敬佩的人。","id":398,"figure":"https://media.prts.wiki/4/46/Avg_avg_npc_033.png"},{"type":"character","name":"avg_npc_033","name2":"avgnew_275_breeze_1#4$1","focus":"2","id":399},{"type":"dialogue","name":"格蕾丝","text":"我......我再去找找别人......","id":400,"figure":"https://media.prts.wiki/0/0d/Avg_avgnew_275_breeze_1-4$1.png"},{"type":"character","name":"avg_npc_033","name2":"avgnew_275_breeze_1#4$1","focus":"1","id":401},{"type":"dialogue","name":"医生","text":"对不起。","id":402,"figure":"https://media.prts.wiki/4/46/Avg_avg_npc_033.png"},{"type":"dialog","id":403},{"type":"blocker","a":"0","r":"0","g":"0","b":"0","fadetime":"0","block":"true","id":404},{"type":"blocker","a":"1","r":"0","g":"0","b":"0","fadetime":"2","block":"true","id":405},{"type":"stopmusic","fadetime":"1","id":406},{"type":"character","id":407},{"type":"background","image":"https://media.prts.wiki/e/e1/Avg_bg_33_g5_srcpark.png","screenadapt":"showall","id":408},{"type":"delay","time":"2","id":409},{"type":"blocker","a":"0","r":"0","g":"0","b":"0","fadetime":"2","block":"true","id":410},{"type":"delay","time":"2","text":"","id":411},{"type":"text","text":"03:44 P.M.","id":412},{"type":"text","text":"多伦郡，岩溪镇，小镇公园","id":413},{"type":"dialog","id":414},{"type":"character","name":"char_empty","id":415},{"type":"playsound","key":"$d_gen_walk_n","volume":"1","id":416},{"type":"move","name":"middle","xpos":"-200","fadetime":"0.3","block":"true","id":417},{"type":"delay","time":"0.51","id":418},{"type":"move","name":"middle","xpos":"200","fadetime":"2","block":"false","id":419},{"type":"character","name":"avgnew_275_breeze_1#4$1","fadetime":"1","id":420},{"type":"delay","time":"2.5","id":421},{"type":"dialogue","name":"格蕾丝","text":"唉......","id":422,"figure":"https://media.prts.wiki/0/0d/Avg_avgnew_275_breeze_1-4$1.png"},{"type":"dialog","id":423},{"type":"character","id":424},{"type":"playsound","key":"$d_avg_crwddiscuss_outside","volume":"0.6","id":425},{"type":"playmusic","intro":"$nervous_intro","key":"https://static.prts.wiki/music/music/act9d0d0/m_avg_nervous_loop.mp3","volume":"0.4","id":426,"musicid":3},{"type":"delay","time":"2.5","id":427},{"type":"dialogue","name":"陌生的镇民","text":"先生们女士们，我再跟大家说一遍，今天我发现这人正在砍我们的树！","id":428},{"type":"dialogue","name":"陌生的镇民","text":"他在破坏我们的财产！","id":429},{"type":"character","name":"avg_npc_242","id":430},{"type":"dialogue","name":"彬彬有礼的先生","text":"......","id":431,"figure":"https://media.prts.wiki/7/7c/Avg_avg_npc_242.png"},{"type":"dialog","id":432},{"type":"character","id":433},{"type":"dialogue","name":"陌生的镇民","text":"今天他们砍了我们的树，明天他们就会抢走我们的食物，后天呢？他们抢走我们的工作，抢走我们的土地！","id":434},{"type":"dialogue","name":"陌生的镇民","text":"我们得捍卫我们的财产！捍卫我们的工作！捍卫我们的小镇！","id":435},{"type":"dialog","id":436},{"type":"camerashake","duration":"0.5","xstrength":"50","ystrength":"50","vibrato":"30","randomness":"90","fadeout":"true","block":"false","id":437},{"type":"dialogue","name":"聚集起来的镇民们","text":"捍卫我们的财产！捍卫我们的工作！捍卫我们的小镇！","id":438},{"type":"dialog","id":439},{"type":"character","name":"avg_npc_242","id":440},{"type":"camerashake","duration":"2","xstrength":"30","ystrength":"30","vibrato":"30","randomness":"90","fadeout":"true","block":"false","id":441},{"type":"playsound","key":"$d_avg_glass_break","volume":"0.3","id":442},{"type":"delay","time":"0.5","id":443},{"type":"move","name":"middle","ypos":"-70","fadetime":"1","isblock":"false","id":444},{"type":"character","fadetime":"0.5","id":445},{"type":"playsound","key":"$d_avg_glass_break","volume":"0.3","id":446},{"type":"delay","time":"0.5","id":447},{"type":"playsound","key":"$d_avg_glass_break","volume":"0.3","id":448},{"type":"delay","time":"0.5","id":449},{"type":"playsound","key":"$d_avg_glass_break","volume":"0.3","id":450},{"type":"delay","time":"2.5","id":451},{"type":"character","id":452},{"type":"playsound","key":"$rungeneral","volume":"1","id":453},{"type":"character","name":"avgnew_275_breeze_1#5$1","fadetime":"1.5","id":454},{"type":"delay","time":"2","text":"","id":455},{"type":"dialogue","name":"格蕾丝","text":"等等，你们这是在干什么？！","id":456,"figure":"https://media.prts.wiki/0/07/Avg_avgnew_275_breeze_1-5$1.png"},{"type":"dialog","id":457},{"type":"character","id":458},{"type":"playsound","key":"$rungeneral","volume":"1","id":459},{"type":"character","name":"avg_npc_177","fadetime":"1.5","id":460},{"type":"delay","time":"2","text":"","id":461},{"type":"dialogue","name":"管家","text":"小姐，别去！","id":462,"figure":"https://media.prts.wiki/a/ae/Avg_avg_npc_177.png"},{"type":"dialog","id":463},{"type":"character","name":"avgnew_275_breeze_1#5$1","name2":"avg_npc_177","focus":"1","id":464},{"type":"dialogue","name":"格蕾丝","text":"康塞尔？你怎么在这里？","id":465,"figure":"https://media.prts.wiki/0/07/Avg_avgnew_275_breeze_1-5$1.png"},{"type":"character","name":"avgnew_275_breeze_1#5$1","name2":"avg_npc_177","focus":"2","id":466},{"type":"dialogue","name":"管家","text":"那个讲话的是佩勒姆家的人，他会认出您来的。","id":467,"figure":"https://media.prts.wiki/a/ae/Avg_avg_npc_177.png"},{"type":"character","name":"avgnew_275_breeze_1#5$1","name2":"avg_npc_177","focus":"1","id":468},{"type":"dialogue","name":"格蕾丝","text":"可被绑起来的那位我也认识，我得把他救下来！","id":469,"figure":"https://media.prts.wiki/0/07/Avg_avgnew_275_breeze_1-5$1.png"},{"type":"character","name":"avgnew_275_breeze_1#5$1","name2":"avg_npc_177","focus":"2","id":470},{"type":"dialogue","name":"管家","text":"......","id":471,"figure":"https://media.prts.wiki/a/ae/Avg_avg_npc_177.png"},{"type":"dialog","id":472},{"type":"character","name":"avgnew_275_breeze_1#5$1","name2":"avg_npc_177","id":473},{"type":"move","name":"left","xpos":"30","fadetime":"0.5","isblock":"false","id":474},{"type":"move","name":"right","xpos":"-30","fadetime":"0.5","isblock":"false","id":475},{"type":"playsound","key":"$d_avg_clothmovement","volume":"1","id":476},{"type":"camerashake","duration":"0.5","xstrength":"30","ystrength":"30","vibrato":"30","randomness":"90","fadeout":"true","block":"true","id":477},{"type":"character","name":"avgnew_275_breeze_1#5$1","name2":"avg_npc_177","focus":"1","id":478},{"type":"dialogue","name":"格蕾丝","text":"松手！","id":479,"figure":"https://media.prts.wiki/0/07/Avg_avgnew_275_breeze_1-5$1.png"},{"type":"character","name":"avgnew_275_breeze_1#5$1","name2":"avg_npc_177","focus":"2","id":480},{"type":"dialogue","name":"管家","text":"小姐......在场的人里有人认识您，那您现在就是亚利桑那家的千金，您的一举一动都代表着整个家族。","id":481,"figure":"https://media.prts.wiki/a/ae/Avg_avg_npc_177.png"},{"type":"dialogue","name":"管家","text":"以您的身份，不能插手这件事。","id":482,"figure":"https://media.prts.wiki/a/ae/Avg_avg_npc_177.png"},{"type":"character","name":"avgnew_275_breeze_1#5$1","name2":"avg_npc_177","focus":"1","id":483},{"type":"dialogue","name":"格蕾丝","text":"如果我说我不在乎呢？","id":484,"figure":"https://media.prts.wiki/0/07/Avg_avgnew_275_breeze_1-5$1.png"},{"type":"character","name":"avgnew_275_breeze_1#5$1","name2":"avg_npc_177","focus":"2","id":485},{"type":"dialogue","name":"管家","text":"但宅子里的仆人们在乎，他们要养家，他们需要稳定的工作。","id":486,"figure":"https://media.prts.wiki/a/ae/Avg_avg_npc_177.png"},{"type":"dialog","id":487},{"type":"character","name":"avgnew_275_breeze_1#5$1","name2":"avg_npc_177","id":488},{"type":"move","name":"left","xpos":"-30","fadetime":"0.5","isblock":"false","id":489},{"type":"move","name":"right","xpos":"30","fadetime":"0.5","isblock":"false","id":490},{"type":"delay","time":"1.5","text":"","id":491},{"type":"character","name":"avgnew_275_breeze_1#4$1","name2":"avg_npc_177","focus":"1","id":492},{"type":"dialogue","name":"格蕾丝","text":"......","id":493,"figure":"https://media.prts.wiki/0/0d/Avg_avgnew_275_breeze_1-4$1.png"},{"type":"dialogue","name":"格蕾丝","text":"看看这些人，他们从来没那么关心过树。","id":494,"figure":"https://media.prts.wiki/0/0d/Avg_avgnew_275_breeze_1-4$1.png"},{"type":"character","name":"avgnew_275_breeze_1#4$1","name2":"avg_npc_177","focus":"2","id":495},{"type":"dialogue","name":"管家","text":"佩勒姆夫人做得很成功，她让镇民打心底开始排斥那些人。她想做的事情，变成了大众想做的事情。","id":496,"figure":"https://media.prts.wiki/a/ae/Avg_avg_npc_177.png"},{"type":"dialogue","name":"管家","text":"如果您此刻执意要冲上去，亚利桑那家族就等同于站到了小镇居民的对立面。","id":497,"figure":"https://media.prts.wiki/a/ae/Avg_avg_npc_177.png"},{"type":"dialogue","name":"管家","text":"这很复杂，如果您真的要干涉这件事，最好等老爷和夫人回来。况且，相信我，他们不会把他绑太久的，那样太危险了。","id":498,"figure":"https://media.prts.wiki/a/ae/Avg_avg_npc_177.png"},{"type":"character","name":"avgnew_275_breeze_1#4$1","name2":"avg_npc_177","focus":"1","id":499},{"type":"dialogue","name":"格蕾丝","text":"......","id":500,"figure":"https://media.prts.wiki/0/0d/Avg_avgnew_275_breeze_1-4$1.png"},{"type":"character","name":"avgnew_275_breeze_1#4$1","name2":"avg_npc_177","focus":"2","id":501},{"type":"dialogue","name":"管家","text":"求您冷静下来，否则我没法向老爷交代......","id":502,"figure":"https://media.prts.wiki/a/ae/Avg_avg_npc_177.png"},{"type":"character","name":"avgnew_275_breeze_1#4$1","name2":"avg_npc_177","focus":"1","id":503},{"type":"dialogue","name":"格蕾丝","text":"我......","id":504,"figure":"https://media.prts.wiki/0/0d/Avg_avgnew_275_breeze_1-4$1.png"},{"type":"dialog","id":505},{"type":"stopmusic","fadetime":"1","id":506},{"type":"delay","time":"1","id":507},{"type":"character","name":"avgnew_275_breeze_1#5$1","name2":"avg_npc_177","focus":"1","id":508},{"type":"dialogue","name":"格蕾丝","text":"我知道了。","id":509,"figure":"https://media.prts.wiki/0/07/Avg_avgnew_275_breeze_1-5$1.png"},{"type":"character","name":"avgnew_275_breeze_1#5$1","name2":"avg_npc_177","focus":"2","id":510},{"type":"dialogue","name":"管家","text":"老爷夫人延期回家的消息没能通知到您的姑姑。她已经在来的路上了，按原计划来为老爷夫人接风洗尘。","id":511,"figure":"https://media.prts.wiki/a/ae/Avg_avg_npc_177.png"},{"type":"dialogue","name":"管家","text":"我们没法让她半路折返......仆人们都快忙疯了，只好精简一下菜单和用餐流程，这才勉强忙得过来......","id":512,"figure":"https://media.prts.wiki/a/ae/Avg_avg_npc_177.png"},{"type":"dialogue","name":"管家","text":"不过宅子里总归需要一位主人才合乎礼节。我就是来找您回去的。","id":513,"figure":"https://media.prts.wiki/a/ae/Avg_avg_npc_177.png"},{"type":"character","name":"avgnew_275_breeze_1#5$1","name2":"avg_npc_177","focus":"1","id":514},{"type":"dialogue","name":"格蕾丝","text":"......看来亚利桑那的大小姐有更重要的事情。","id":515,"figure":"https://media.prts.wiki/0/07/Avg_avgnew_275_breeze_1-5$1.png"},{"type":"character","name":"avgnew_275_breeze_1#5$1","name2":"avg_npc_177","focus":"2","id":516},{"type":"dialogue","name":"管家","text":"请跟我来，宅子需要您。","id":517,"figure":"https://media.prts.wiki/a/ae/Avg_avg_npc_177.png"},{"type":"dialog","id":518},{"type":"character","fadetime":"1.5","id":519},{"type":"delay","time":"2","id":520},{"type":"character","name":"avgnew_275_breeze_1#4$1","fadetime":"1","id":521},{"type":"delay","time":"1.5","id":522},{"type":"dialogue","name":"格蕾丝","text":"可是......","id":523,"figure":"https://media.prts.wiki/0/0d/Avg_avgnew_275_breeze_1-4$1.png"},{"type":"dialog","id":524},{"type":"delay","time":"1.5","id":525},{"type":"character","fadetime":"1.5","id":526},{"type":"delay","time":"2","id":527},{"type":"character","name":"avg_npc_242","fadetime":"1","id":528},{"type":"delay","time":"1.5","id":529},{"type":"blocker","a":"0","r":"0","g":"0","b":"0","fadetime":"0","block":"true","id":530},{"type":"blocker","a":"0.6","r":"0","g":"0","b":"0","fadetime":"0.8","block":"true","id":531},{"type":"subtitle","text":"那个男人始终低着头，但格蕾丝却能感到一道目光直射而来，刺痛，就像一把利剑穿透她的身体。","x":"300","y":"370","alignment":"left","size":"24","delay":"0.04","width":"700","id":532},{"type":"subtitle","text":"一种对于她这样的年轻女孩而言过于深沉的悲哀正在她体内疯狂蔓延。","x":"300","y":"370","alignment":"left","size":"24","delay":"0.04","width":"700","id":533},{"type":"subtitle","id":534},{"type":"character","fadetime":"0.8","id":535},{"type":"blocker","a":"0","r":"0","g":"0","b":"0","fadetime":"0.8","block":"true","id":536},{"type":"delay","time":"1","id":537},{"type":"character","name":"avgnew_275_breeze_1#4$1","id":538},{"type":"dialogue","name":"格蕾丝","text":"......","id":539,"figure":"https://media.prts.wiki/0/0d/Avg_avgnew_275_breeze_1-4$1.png"},{"type":"dialog","id":540},{"type":"blocker","a":"0","r":"0","g":"0","b":"0","fadetime":"0","block":"true","id":541},{"type":"blocker","a":"1","r":"0","g":"0","b":"0","fadetime":"2","block":"true","id":542},{"type":"stopmusic","fadetime":"1","id":543},{"type":"character","id":544},{"type":"background","image":"https://media.prts.wiki/2/2e/Avg_bg_32_g11_victoriaroom_n.png","screenadapt":"showall","id":545},{"type":"delay","time":"2","id":546},{"type":"playmusic","intro":"$path_intro","key":"https://static.prts.wiki/music/music/a001/m_dia_path_loop.mp3","volume":"0.4","id":547,"musicid":4},{"type":"blocker","a":"0","r":"0","g":"0","b":"0","fadetime":"2","block":"true","id":548},{"type":"delay","time":"2","text":"","id":549},{"type":"text","text":"04:12 P.M.","id":550},{"type":"text","text":"多伦郡，岩溪镇北，亚利桑那宅邸","id":551},{"type":"dialog","id":552},{"type":"playsound","key":"$d_avg_cloakmovement","volume":"1","id":553},{"type":"delay","time":"2","id":554},{"type":"character","name":"avg_npc_243","id":555},{"type":"dialogue","name":"女仆","text":"这件不行......这件也不行......","id":556,"figure":"https://media.prts.wiki/5/5e/Avg_avg_npc_243.png"},{"type":"dialog","id":557},{"type":"character","id":558},{"type":"playsound","key":"$d_avg_clothmovement","volume":"1","id":559},{"type":"delay","time":"2","id":560},{"type":"character","name":"avg_npc_243","id":561},{"type":"dialogue","name":"女仆","text":"这件......","id":562,"figure":"https://media.prts.wiki/5/5e/Avg_avg_npc_243.png"},{"type":"character","name":"avgnew_275_breeze_1#4$1","id":563},{"type":"dialogue","name":"格蕾丝","text":"就穿之前那套不行吗？","id":564,"figure":"https://media.prts.wiki/0/0d/Avg_avgnew_275_breeze_1-4$1.png"},{"type":"character","name":"avg_npc_243","id":565},{"type":"dialogue","name":"女仆","text":"您最近有点过于忙碌，皮肤状态不是很好，我得帮您找一套比较提气色的。","id":566,"figure":"https://media.prts.wiki/5/5e/Avg_avg_npc_243.png"},{"type":"character","name":"avgnew_275_breeze_1#4$1","id":567},{"type":"dialogue","name":"格蕾丝","text":"......","id":568,"figure":"https://media.prts.wiki/0/0d/Avg_avgnew_275_breeze_1-4$1.png"},{"type":"dialog","id":569},{"type":"character","id":570},{"type":"playsound","key":"$doorknockquite","volume":"1","id":571},{"type":"delay","time":"2","id":572},{"type":"dialogue","name":"管家","text":"客人大概七分钟后就要到了，我们得去门口集合了。","id":573},{"type":"dialog","id":574},{"type":"character","name":"avg_npc_243","id":575},{"type":"dialogue","name":"女仆","text":"别催，康塞尔先生！","id":576,"figure":"https://media.prts.wiki/5/5e/Avg_avg_npc_243.png"},{"type":"character","name":"avgnew_275_breeze_1#4$1","id":577},{"type":"dialogue","name":"格蕾丝","text":"......","id":578,"figure":"https://media.prts.wiki/0/0d/Avg_avgnew_275_breeze_1-4$1.png"},{"type":"character","name":"avg_npc_243","id":579},{"type":"dialogue","name":"女仆","text":"小姐，我找到了，就这条吧！","id":580,"figure":"https://media.prts.wiki/5/5e/Avg_avg_npc_243.png"},{"type":"dialog","id":581},{"type":"character","id":582},{"type":"character","name":"avgnew_275_breeze_1#4$1","fadetime":"1","id":583},{"type":"delay","time":"1.5","id":584},{"type":"text","text":"“小姐”没有回应，她此刻正斜靠在椅子上望向窗外，仆人们已经开始准备列队欢迎宾客。","id":585},{"type":"text","text":"她又将目光投向远方，小镇的工厂生机勃勃地向天空喷吐着黑烟。","id":586},{"type":"text","text":"安静......","id":587},{"type":"character","name":"avgnew_275_breeze_1#5$1","id":588},{"type":"text","text":"盛夏与严冬都无法如约而至。","id":589},{"type":"text","text":"最后，她的目光回到近处的梳妆台上。今天早上刚送来的信，依然静静地躺着。","id":590},{"type":"dialog","id":591},{"type":"character","fadetime":"1.5","id":592},{"type":"delay","time":"2","id":593},{"type":"character","name":"avg_npc_243","id":594},{"type":"dialogue","name":"女仆","text":"这条裙子，下午我刚刚帮您修补过，看看这些新缝上去的小亮片！","id":595,"figure":"https://media.prts.wiki/5/5e/Avg_avg_npc_243.png"},{"type":"dialogue","name":"女仆","text":"小姐，您要读信了吗？我帮您拿拆信刀来。","id":596,"figure":"https://media.prts.wiki/5/5e/Avg_avg_npc_243.png"},{"type":"character","name":"avgnew_275_breeze_1#4$1","id":597},{"type":"dialogue","name":"格蕾丝","text":"不用，我已经打开了......","id":598,"figure":"https://media.prts.wiki/0/0d/Avg_avgnew_275_breeze_1-4$1.png"},{"type":"dialog","id":599},{"type":"stopmusic","fadetime":"1","id":600},{"type":"playsound","key":"$d_avg_paper1","id":601},{"type":"delay","time":"2.5","id":602},{"type":"character","name":"avgnew_275_breeze_1#2$1","id":603},{"type":"delay","time":"1","id":604},{"type":"blocker","a":"0","r":"0","g":"0","b":"0","fadetime":"0","block":"true","id":605},{"type":"blocker","a":"1","r":"0","g":"0","b":"0","fadetime":"2","block":"true","id":606},{"type":"stopmusic","fadetime":"1","id":607},{"type":"character","id":608},{"type":"background","image":"https://media.prts.wiki/1/1c/Avg_bg_bg_manorindoor.png","screenadapt":"showall","id":609},{"type":"delay","time":"2","id":610},{"type":"playmusic","intro":"$drift_intro","key":"https://static.prts.wiki/music/music/act9d0d0/m_avg_drift_loop.mp3","volume":"0","id":611,"musicid":5},{"type":"blocker","a":"0","r":"0","g":"0","b":"0","fadetime":"2","block":"true","id":612},{"type":"delay","time":"2","text":"","id":613},{"type":"character","name":"avg_npc_177","fadetime":"1.5","id":614},{"type":"delay","time":"2","id":615},{"type":"move","name":"middle","xpos":"50","fadetime":"1.5","isblock":"true","id":616},{"type":"playsound","key":"$d_avg_cloakmovement","id":617},{"type":"delay","time":"1","id":618},{"type":"move","name":"middle","xpos":"-50","fadetime":"1.5","isblock":"true","id":619},{"type":"playsound","key":"$d_avg_flag","id":620},{"type":"delay","time":"1.5","id":621},{"type":"move","name":"middle","ypos":"-10","fadetime":"1.5","isblock":"true","id":622},{"type":"playsound","key":"$d_avg_dishes","id":623},{"type":"delay","time":"2","id":624},{"type":"move","name":"middle","ypos":"10","fadetime":"1.5","isblock":"true","id":625},{"type":"delay","time":"1.5","id":626},{"type":"character","id":627},{"type":"camerashake","duration":"0.3","xstrength":"30","ystrength":"30","vibrato":"30","randomness":"90","fadeout":"true","block":"false","id":628},{"type":"dialogue","name":"女仆","text":"康塞尔先生，快拦住大小姐！！","id":629},{"type":"character","name":"avg_npc_177","id":630},{"type":"dialogue","name":"管家","text":"啊？","id":631,"figure":"https://media.prts.wiki/a/ae/Avg_avg_npc_177.png"},{"type":"dialog","id":632},{"type":"character","id":633},{"type":"character","name":"char_empty","id":634},{"type":"move","name":"middle","xpos":"200","fadetime":"0.3","block":"true","id":635},{"type":"delay","time":"0.51","id":636},{"type":"move","name":"middle","xpos":"-200","fadetime":"1","block":"false","id":637},{"type":"character","name":"avgnew_275_breeze_1#5$1","fadetime":"0.7","id":638},{"type":"delay","time":"1.1","id":639},{"type":"playsound","key":"$rungeneral","volume":"1","id":640},{"type":"move","name":"middle","xpos":"-300","fadetime":"2","block":"false","id":641},{"type":"character","fadetime":"0.5","id":642},{"type":"delay","time":"2","id":643},{"type":"playsound","key":"$d_gen_walk_n","id":644},{"type":"character","name":"avg_npc_243","fadetime":"1.5","id":645},{"type":"delay","time":"2","id":646},{"type":"dialogue","name":"女仆","text":"呼......呼......咳咳......咳咳......我跑不动了，快......","id":647,"figure":"https://media.prts.wiki/5/5e/Avg_avg_npc_243.png"},{"type":"character","name":"avg_npc_177","id":648},{"type":"dialogue","name":"管家","text":"叫新来的男仆帮我把这里的东西整理完。","id":649,"figure":"https://media.prts.wiki/a/ae/Avg_avg_npc_177.png"},{"type":"dialog","id":650},{"type":"delay","time":"0.7","id":651},{"type":"playsound","key":"$rungeneral","volume":"1","id":652},{"type":"move","name":"middle","xpos":"-300","fadetime":"2","block":"false","id":653},{"type":"character","fadetime":"0.5","id":654},{"type":"delay","time":"1.5","id":655},{"type":"blocker","a":"0","r":"0","g":"0","b":"0","fadetime":"0","block":"true","id":656},{"type":"blocker","a":"1","r":"0","g":"0","b":"0","fadetime":"2","block":"true","id":657},{"type":"character","id":658},{"type":"background","image":"https://media.prts.wiki/8/87/Avg_bg_25_mini02_victoria_street_n.png","screenadapt":"showall","id":659},{"type":"delay","time":"2","id":660},{"type":"blocker","a":"0","r":"0","g":"0","b":"0","fadetime":"2","block":"true","id":661},{"type":"musicvolume","volume":"0.6","fadetime":"2","id":662},{"type":"delay","time":"2","text":"","id":663},{"type":"character","name":"avg_npc_177","name2":"char_empty","id":664},{"type":"playsound","key":"$rungeneral","volume":"1","id":665},{"type":"move","name":"right","xpos":"200","fadetime":"0.3","block":"true","id":666},{"type":"delay","time":"0.51","id":667},{"type":"move","name":"right","xpos":"-200","fadetime":"1","block":"false","id":668},{"type":"character","name":"avg_npc_177","name2":"avgnew_275_breeze_1#5$1","fadetime":"0.7","id":669},{"type":"delay","time":"1.2","id":670},{"type":"character","name":"avg_npc_177","name2":"avgnew_275_breeze_1#5$1","focus":"2","id":671},{"type":"dialogue","name":"格蕾丝","text":"......让开！","id":672,"figure":"https://media.prts.wiki/0/07/Avg_avgnew_275_breeze_1-5$1.png"},{"type":"character","name":"avg_npc_177","name2":"avgnew_275_breeze_1#5$1","focus":"1","id":673},{"type":"dialogue","name":"管家","text":"小姐，晚宴马上就要开始了，为了亚利桑那，我不能让您乱跑。","id":674,"figure":"https://media.prts.wiki/a/ae/Avg_avg_npc_177.png"},{"type":"character","name":"avg_npc_177","name2":"avgnew_275_breeze_1#5$1","focus":"2","id":675},{"type":"dialogue","name":"格蕾丝","text":"......","id":676,"figure":"https://media.prts.wiki/0/07/Avg_avgnew_275_breeze_1-5$1.png"},{"type":"character","name":"avg_npc_177","name2":"avgnew_275_breeze_1#5$1","focus":"1","id":677},{"type":"dialogue","name":"管家","text":"小姐，发生什么事了吗？","id":678,"figure":"https://media.prts.wiki/a/ae/Avg_avg_npc_177.png"},{"type":"character","name":"avg_npc_177","name2":"avgnew_275_breeze_1#5$1","focus":"2","id":679},{"type":"dialogue","name":"格蕾丝","text":"让开！","id":680,"figure":"https://media.prts.wiki/0/07/Avg_avgnew_275_breeze_1-5$1.png"},{"type":"character","name":"avg_npc_177","name2":"avgnew_275_breeze_1#5$1","focus":"1","id":681},{"type":"dialogue","name":"管家","text":"到底发生了什么？您得告诉我，我才能选择是否要听从您。","id":682,"figure":"https://media.prts.wiki/a/ae/Avg_avg_npc_177.png"},{"type":"character","name":"avg_npc_177","name2":"avgnew_275_breeze_1#4$1","focus":"2","id":683},{"type":"dialogue","name":"格蕾丝","text":"......","id":684,"figure":"https://media.prts.wiki/0/0d/Avg_avgnew_275_breeze_1-4$1.png"},{"type":"dialogue","name":"格蕾丝","text":"有信使在森林里发现了一些......","id":685,"figure":"https://media.prts.wiki/0/0d/Avg_avgnew_275_breeze_1-4$1.png"},{"type":"dialogue","name":"格蕾丝","text":"其中有个女孩身上携带了很多的信，没写内容但是寄信人和收信人都已经填好。收信人是我，寄信人是......","id":686,"figure":"https://media.prts.wiki/0/0d/Avg_avgnew_275_breeze_1-4$1.png"},{"type":"dialogue","name":"格蕾丝","text":"玛丽安......两周前就......","id":687,"figure":"https://media.prts.wiki/0/0d/Avg_avgnew_275_breeze_1-4$1.png"},{"type":"dialog","id":688},{"type":"character","name":"avg_npc_177","name2":"avgnew_275_breeze_1#4$1","id":689},{"type":"delay","time":"0.2","id":690},{"type":"move","name":"left","xpos":"60","ypos":"-10","fadetime":"1.5","isblock":"false","id":691},{"type":"move","name":"right","xpos":"-40","ypos":"-20","fadetime":"0.5","isblock":"false","id":692},{"type":"playsound","key":"$d_avg_clothmovement","volume":"1","id":693},{"type":"delay","time":"2","id":694},{"type":"character","name":"avg_npc_177","name2":"avgnew_275_breeze_1#4$1","focus":"1","id":695},{"type":"dialogue","name":"管家","text":"小姐......请节哀......","id":696,"figure":"https://media.prts.wiki/a/ae/Avg_avg_npc_177.png"},{"type":"character","name":"avg_npc_177","name2":"avgnew_275_breeze_1#4$1","focus":"2","id":697},{"type":"dialogue","name":"格蕾丝","text":"都是我的错......","id":698,"figure":"https://media.prts.wiki/0/0d/Avg_avgnew_275_breeze_1-4$1.png"},{"type":"character","name":"avg_npc_177","name2":"avgnew_275_breeze_1#4$1","focus":"1","id":699},{"type":"dialogue","name":"管家","text":"这不是您的错，您的努力我都看在眼里。","id":700,"figure":"https://media.prts.wiki/a/ae/Avg_avg_npc_177.png"},{"type":"dialog","id":701},{"type":"character","name":"avg_npc_177","name2":"avgnew_275_breeze_1#4$1","id":702},{"type":"delay","time":"0.2","id":703},{"type":"move","name":"left","xpos":"-40","ypos":"10","fadetime":"1","isblock":"false","id":704},{"type":"move","name":"right","xpos":"40","ypos":"20","fadetime":"1.5","isblock":"false","id":705},{"type":"playsound","key":"$d_avg_clothmovement","volume":"1","id":706},{"type":"delay","time":"2","id":707},{"type":"character","name":"avg_npc_177","name2":"avgnew_275_breeze_1#4$1","focus":"2","id":708},{"type":"dialogue","name":"格蕾丝","text":"是吗？我到底努力了什么......？","id":709,"figure":"https://media.prts.wiki/0/0d/Avg_avgnew_275_breeze_1-4$1.png"},{"type":"dialogue","name":"格蕾丝","text":"最早的时候，我对他们的情况缺乏基本的认知。","id":710,"figure":"https://media.prts.wiki/0/0d/Avg_avgnew_275_breeze_1-4$1.png"},{"type":"dialogue","name":"格蕾丝","text":"我能感受到他们在受苦，却没法感受得那么深刻。我相信总有人会帮忙，他们总会好起来。","id":711,"figure":"https://media.prts.wiki/0/0d/Avg_avgnew_275_breeze_1-4$1.png"},{"type":"dialogue","name":"格蕾丝","text":"前几个月，我不过是在扮演好亚利桑那大小姐之余抽空写了一些信而已，从结果来看，这一切都没有什么意义。","id":712,"figure":"https://media.prts.wiki/0/0d/Avg_avgnew_275_breeze_1-4$1.png"},{"type":"dialogue","name":"格蕾丝","text":"但这几天我真正和他们接触下来，我才意识到我曾经自认为能共情的苦痛，不及现实的万分之一。","id":713,"figure":"https://media.prts.wiki/0/0d/Avg_avgnew_275_breeze_1-4$1.png"},{"type":"dialogue","name":"格蕾丝","text":"康塞尔，他们需要帮助。他们没必要走上和玛丽安一样的路。","id":714,"figure":"https://media.prts.wiki/0/0d/Avg_avgnew_275_breeze_1-4$1.png"},{"type":"character","name":"avg_npc_177","name2":"avgnew_275_breeze_1#4$1","focus":"1","id":715},{"type":"dialogue","name":"管家","text":"那也不该是您去，您毕竟是亚利桑那家的大小姐。","id":716,"figure":"https://media.prts.wiki/a/ae/Avg_avg_npc_177.png"},{"type":"character","name":"avg_npc_177","name2":"avgnew_275_breeze_1#4$1","focus":"2","id":717},{"type":"dialogue","name":"格蕾丝","text":"没有大小姐和平民，康塞尔。在此等苦难面前，只有人与人。","id":718,"figure":"https://media.prts.wiki/0/0d/Avg_avgnew_275_breeze_1-4$1.png"},{"type":"character","name":"avg_npc_177","name2":"avgnew_275_breeze_1#4$1","focus":"1","id":719},{"type":"dialogue","name":"管家","text":"小姐，老爷和夫人知道这些事吗？","id":720,"figure":"https://media.prts.wiki/a/ae/Avg_avg_npc_177.png"},{"type":"character","name":"avg_npc_177","name2":"avgnew_275_breeze_1#4$1","focus":"2","id":721},{"type":"dialogue","name":"格蕾丝","text":"不知道。我怕他们生气，那样我就更是什么也做不了了。","id":722,"figure":"https://media.prts.wiki/0/0d/Avg_avgnew_275_breeze_1-4$1.png"},{"type":"character","name":"avg_npc_177","name2":"avgnew_275_breeze_1#4$1","focus":"1","id":723},{"type":"dialogue","name":"管家","text":"也许等老爷和夫人回家后，您可以告诉他们。","id":724,"figure":"https://media.prts.wiki/a/ae/Avg_avg_npc_177.png"},{"type":"character","name":"avg_npc_177","name2":"avgnew_275_breeze_1#4$1","focus":"2","id":725},{"type":"dialogue","name":"格蕾丝","text":"......不。","id":726,"figure":"https://media.prts.wiki/0/0d/Avg_avgnew_275_breeze_1-4$1.png"},{"type":"character","name":"avg_npc_177","name2":"avgnew_275_breeze_1#5$1","focus":"2","id":727},{"type":"dialogue","name":"格蕾丝","text":"我今天听到了一些关于老爹老妈的事......","id":728,"figure":"https://media.prts.wiki/0/07/Avg_avgnew_275_breeze_1-5$1.png"},{"type":"dialogue","name":"格蕾丝","text":"我不认为他们与我之前花时间写信去求助的那些人有什么差别......","id":729,"figure":"https://media.prts.wiki/0/07/Avg_avgnew_275_breeze_1-5$1.png"},{"type":"dialogue","name":"格蕾丝","text":"贵族们的爱情是虚假的，贵族们的仁慈是虚假的......连邵先生都骗了我......","id":730,"figure":"https://media.prts.wiki/0/07/Avg_avgnew_275_breeze_1-5$1.png"},{"type":"character","name":"avg_npc_177","name2":"avgnew_275_breeze_1#4$1","focus":"2","id":731},{"type":"dialogue","name":"格蕾丝","text":"不过也多亏了邵先生，他要我去那些人中间，帮他们检查一下健康状况，给他们一点基础的用药建议。","id":732,"figure":"https://media.prts.wiki/0/0d/Avg_avgnew_275_breeze_1-4$1.png"},{"type":"dialogue","name":"格蕾丝","text":"今天去的时候，我发现一些人的健康状况有所好转。","id":733,"figure":"https://media.prts.wiki/0/0d/Avg_avgnew_275_breeze_1-4$1.png"},{"type":"dialogue","name":"格蕾丝","text":"我相信，这才是真正在做事......至少对我来说，这才是真正有意义的事业。","id":734,"figure":"https://media.prts.wiki/0/0d/Avg_avgnew_275_breeze_1-4$1.png"},{"type":"character","name":"avg_npc_177","name2":"avgnew_275_breeze_1#5$1","focus":"2","id":735},{"type":"dialogue","name":"格蕾丝","text":"我为什么还要去“等”别人来做什么？我不能把别人活下去的希望交到那些人手上，我不能自我欺骗，一再拖延。","id":736,"figure":"https://media.prts.wiki/0/07/Avg_avgnew_275_breeze_1-5$1.png"},{"type":"character","name":"avg_npc_177","name2":"avgnew_275_breeze_1#5$1","focus":"1","id":737},{"type":"dialogue","name":"管家","text":"小姐，我们应该等老爷和夫人——","id":738,"figure":"https://media.prts.wiki/a/ae/Avg_avg_npc_177.png"},{"type":"character","name":"avgnew_275_breeze_1#5$1","id":739},{"type":"camerashake","duration":"0.3","xstrength":"30","ystrength":"30","vibrato":"30","randomness":"90","fadeout":"true","block":"false","id":740},{"type":"dialogue","name":"格蕾丝","text":"你还要我等多久？！","id":741,"figure":"https://media.prts.wiki/0/07/Avg_avgnew_275_breeze_1-5$1.png"},{"type":"dialogue","name":"格蕾丝","text":"我的朋友死了！当她挣扎于生死间的时候，我却在忙着社交，忙着思考我的措辞，忙着理清亚利桑那与其他贵族的人际关系！","id":742,"figure":"https://media.prts.wiki/0/07/Avg_avgnew_275_breeze_1-5$1.png"},{"type":"character","name":"avgnew_275_breeze_1#5$1","id":743},{"type":"dialogue","name":"格蕾丝","text":"我需要一直待在家里，需要用愚蠢无用的体面方式求援，我甚至只能眼睁睁看着信任我的人遭受私刑......","id":744,"figure":"https://media.prts.wiki/0/07/Avg_avgnew_275_breeze_1-5$1.png"},{"type":"dialogue","name":"格蕾丝","text":"康塞尔......贵族的身份又何尝不是一种束缚。","id":745,"figure":"https://media.prts.wiki/0/07/Avg_avgnew_275_breeze_1-5$1.png"},{"type":"character","name":"avg_npc_177","id":746},{"type":"dialogue","name":"管家","text":"小姐，这些社交也好，礼仪也罢，都是为了让这个家族能重返荣耀。若能回到过去的状态，亚利桑那的光芒必然能照耀到更多的人。","id":747,"figure":"https://media.prts.wiki/a/ae/Avg_avg_npc_177.png"},{"type":"character","name":"avgnew_275_breeze_1#5$1","id":748},{"type":"dialogue","name":"格蕾丝","text":"那些人等不到太阳升起，我也是。","id":749,"figure":"https://media.prts.wiki/0/07/Avg_avgnew_275_breeze_1-5$1.png"},{"type":"dialogue","name":"格蕾丝","text":"而且我听说他们是因为被剥夺了土地才不得不流浪的，康塞尔。他们每一个人，都会像玛丽安一样，在我享乐时慢慢死去......","id":750,"figure":"https://media.prts.wiki/0/07/Avg_avgnew_275_breeze_1-5$1.png"},{"type":"dialogue","name":"格蕾丝","text":"若生活还得看那些贵族的脸色，日升日落，最终又有什么意义？如果他们能恢复健康，他们便能在黑暗中举起火把，自己找到出路。","id":751,"figure":"https://media.prts.wiki/0/07/Avg_avgnew_275_breeze_1-5$1.png"},{"type":"dialog","id":752},{"type":"character","id":753},{"type":"character","name":"avg_npc_177","name2":"avgnew_275_breeze_1#4$1","focus":"1","id":754},{"type":"dialogue","name":"管家","text":"小姐......","id":755,"figure":"https://media.prts.wiki/a/ae/Avg_avg_npc_177.png"},{"type":"character","name":"avg_npc_177","name2":"avgnew_275_breeze_1#4$1","focus":"2","id":756},{"type":"dialogue","name":"格蕾丝","text":"抱歉，康塞尔。我不是在对着你生气......","id":757,"figure":"https://media.prts.wiki/0/0d/Avg_avgnew_275_breeze_1-4$1.png"},{"type":"dialogue","name":"格蕾丝","text":"你就当我想找点事情排解一下我的悲伤，就像有些人喝酒或打猎一样。","id":758,"figure":"https://media.prts.wiki/0/0d/Avg_avgnew_275_breeze_1-4$1.png"},{"type":"dialogue","name":"格蕾丝","text":"我真的得做点什么，而不是留在那个场合，一成不变地活着。","id":759,"figure":"https://media.prts.wiki/0/0d/Avg_avgnew_275_breeze_1-4$1.png"},{"type":"dialogue","name":"格蕾丝","text":"至少让我在这几天里做个有用的人吧......","id":760,"figure":"https://media.prts.wiki/0/0d/Avg_avgnew_275_breeze_1-4$1.png"},{"type":"character","name":"avg_npc_177","name2":"avgnew_275_breeze_1#4$1","focus":"1","id":761},{"type":"dialogue","name":"管家","text":"......","id":762,"figure":"https://media.prts.wiki/a/ae/Avg_avg_npc_177.png"},{"type":"dialogue","name":"管家","text":"我明白了，那您一定需要这些书。","id":763,"figure":"https://media.prts.wiki/a/ae/Avg_avg_npc_177.png"},{"type":"dialog","id":764},{"type":"move","name":"left","xpos":"10","fadetime":"1","isblock":"true","id":765},{"type":"playsound","key":"$d_avg_clothmovement","volume":"1","id":766},{"type":"move","name":"left","xpos":"-10","fadetime":"1","isblock":"true","id":767},{"type":"character","name":"avg_npc_177","name2":"avgnew_275_breeze_1#2$1","focus":"2","id":768},{"type":"dialogue","name":"格蕾丝","text":"这是......","id":769,"figure":"https://media.prts.wiki/e/ed/Avg_avgnew_275_breeze_1-2$1.png"},{"type":"character","name":"avg_npc_177","name2":"avgnew_275_breeze_1#2$1","focus":"1","id":770},{"type":"dialogue","name":"管家","text":"书房里的，您应该记得吧？老爷翻译的，您之前已经翻阅过无数遍了。","id":771,"figure":"https://media.prts.wiki/a/ae/Avg_avg_npc_177.png"},{"type":"dialogue","name":"管家","text":"即使翻过无数遍，也会忘记其中的细节，您带着这些书，好歹有个参考。","id":772,"figure":"https://media.prts.wiki/a/ae/Avg_avg_npc_177.png"},{"type":"character","name":"avg_npc_177","name2":"avgnew_275_breeze_1#2$1","focus":"2","id":773},{"type":"dialogue","name":"格蕾丝","text":"康塞尔......你......","id":774,"figure":"https://media.prts.wiki/e/ed/Avg_avgnew_275_breeze_1-2$1.png"},{"type":"character","name":"avg_npc_177","name2":"avgnew_275_breeze_1#2$1","focus":"1","id":775},{"type":"dialogue","name":"管家","text":"我很熟悉这种场景，我拦不住您的。","id":776,"figure":"https://media.prts.wiki/a/ae/Avg_avg_npc_177.png"},{"type":"dialogue","name":"管家","text":"我会说我没能追上您，您也别跟他们说是我故意让您走的就行。","id":777,"figure":"https://media.prts.wiki/a/ae/Avg_avg_npc_177.png"},{"type":"character","name":"avg_npc_177","name2":"avgnew_275_breeze_1#4$1","focus":"2","id":778},{"type":"dialogue","name":"格蕾丝","text":"......谢谢。","id":779,"figure":"https://media.prts.wiki/0/0d/Avg_avgnew_275_breeze_1-4$1.png"},{"type":"dialog","id":780},{"type":"playsound","key":"$d_gen_walk_n","id":781},{"type":"character","name":"avg_npc_177","name2":"char_empty","fadetime":"1.5","id":782},{"type":"delay","time":"2","id":783},{"type":"character","name":"avg_npc_177","name2":"char_empty","focus":"1","id":784},{"type":"dialogue","name":"管家","text":"等等，小姐。","id":785,"figure":"https://media.prts.wiki/a/ae/Avg_avg_npc_177.png"},{"type":"character","name":"avgnew_275_breeze_1#2$1","id":786},{"type":"dialogue","name":"格蕾丝","text":"你该不会反悔了吧，康塞尔？","id":787,"figure":"https://media.prts.wiki/e/ed/Avg_avgnew_275_breeze_1-2$1.png"},{"type":"character","name":"avg_npc_177","id":788},{"type":"dialogue","name":"管家","text":"我去邵先生家里回收了您留在那的“玩具”。","id":789,"figure":"https://media.prts.wiki/a/ae/Avg_avg_npc_177.png"},{"type":"dialogue","name":"管家","text":"还有，邵先生跟我说，如果见到“亚利桑那小姐的沃尔珀朋友”，告诉她，诊所的窗户开着，翻进去后，药物和各种工具都可以自取。","id":790,"figure":"https://media.prts.wiki/a/ae/Avg_avg_npc_177.png"},{"type":"character","name":"avgnew_275_breeze_1#4$1","id":791},{"type":"dialogue","name":"格蕾丝","text":"......嗯......","id":792,"figure":"https://media.prts.wiki/0/0d/Avg_avgnew_275_breeze_1-4$1.png"},{"type":"character","name":"avg_npc_177","id":793},{"type":"dialogue","name":"管家","text":"小姐，您这样离开，就藏不住了。老爷回来后，您想过怎么办吗？我不认为吵架可以解决问题。","id":794,"figure":"https://media.prts.wiki/a/ae/Avg_avg_npc_177.png"},{"type":"character","name":"avgnew_275_breeze_1#1$1","id":795},{"type":"dialogue","name":"格蕾丝","text":"我会认错的，还不是和他吵架的时候。","id":796,"figure":"https://media.prts.wiki/3/3a/Avg_avgnew_275_breeze_1-1$1.png"},{"type":"character","name":"avg_npc_177","id":797},{"type":"dialogue","name":"管家","text":"请您注意安全，以及注意隐藏您的身份。","id":798,"figure":"https://media.prts.wiki/a/ae/Avg_avg_npc_177.png"},{"type":"character","name":"avgnew_275_breeze_1#6$1","id":799},{"type":"dialogue","name":"格蕾丝","text":"谢谢，康塞尔。","id":800,"figure":"https://media.prts.wiki/9/9b/Avg_avgnew_275_breeze_1-6$1.png"},{"type":"dialog","id":801},{"type":"blocker","a":"0","r":"0","g":"0","b":"0","fadetime":"0","block":"true","id":802},{"type":"blocker","a":"1","r":"0","g":"0","b":"0","fadetime":"2","block":"true","id":803},{"type":"stopmusic","fadetime":"1","id":804},{"type":"character","id":805},{"type":"background","image":"https://media.prts.wiki/1/1c/Avg_bg_bg_manorindoor.png","screenadapt":"showall","id":806},{"type":"delay","time":"2.5","id":807},{"type":"playmusic","intro":"$warm_intro","key":"https://static.prts.wiki/music/music/act9d0d0/m_avg_warm_loop.mp3","volume":"0.4","id":808,"musicid":6},{"type":"blocker","a":"0","r":"0","g":"0","b":"0","fadetime":"2","block":"true","id":809},{"type":"delay","time":"2","text":"","id":810},{"type":"character","name":"avg_npc_177","name2":"char_empty","id":811},{"type":"playsound","key":"$d_gen_walk_n","volume":"1","id":812},{"type":"move","name":"right","xpos":"200","fadetime":"0.3","block":"true","id":813},{"type":"delay","time":"0.51","id":814},{"type":"move","name":"right","xpos":"-200","fadetime":"1.5","block":"false","id":815},{"type":"character","name":"avg_npc_177","name2":"avg_npc_243","fadetime":"1","id":816},{"type":"delay","time":"2","id":817},{"type":"character","name":"avg_npc_177","name2":"avg_npc_243","focus":"1","id":818},{"type":"dialogue","name":"管家","text":"我们的大小姐还在书房里吗？","id":819,"figure":"https://media.prts.wiki/a/ae/Avg_avg_npc_177.png"},{"type":"character","name":"avg_npc_177","name2":"avg_npc_243","focus":"2","id":820},{"type":"dialogue","name":"女仆","text":"是的，她和以前真是天差地别。","id":821,"figure":"https://media.prts.wiki/5/5e/Avg_avg_npc_243.png"},{"type":"character","name":"avg_npc_177","name2":"avg_npc_243","focus":"1","id":822},{"type":"dialogue","name":"管家","text":"我也许做了一件坏事，要害你失业了。","id":823,"figure":"https://media.prts.wiki/a/ae/Avg_avg_npc_177.png"},{"type":"character","name":"avg_npc_177","name2":"avg_npc_243","focus":"2","id":824},{"type":"dialogue","name":"女仆","text":"失业？小姐现在这么乖，都不往外跑了，反而天天泡在书房里，我怎么可能失业？","id":825,"figure":"https://media.prts.wiki/5/5e/Avg_avg_npc_243.png"},{"type":"character","name":"avg_npc_177","name2":"avg_npc_243","focus":"1","id":826},{"type":"dialogue","name":"管家","text":"千万次的离开都比不上一次有目的的远行。她已经不是以前那个小女孩了。","id":827,"figure":"https://media.prts.wiki/a/ae/Avg_avg_npc_177.png"},{"type":"character","name":"avg_npc_177","name2":"avg_npc_243","focus":"2","id":828},{"type":"dialogue","name":"女仆","text":"谢天谢地。","id":829,"figure":"https://media.prts.wiki/5/5e/Avg_avg_npc_243.png"},{"type":"character","name":"avg_npc_177","name2":"avg_npc_243","focus":"1","id":830},{"type":"dialogue","name":"管家","text":"你不会感到不安？","id":831,"figure":"https://media.prts.wiki/a/ae/Avg_avg_npc_177.png"},{"type":"character","name":"avg_npc_177","name2":"avg_npc_243","focus":"2","id":832},{"type":"dialogue","name":"女仆","text":"既然已经这样了......如果小姐想这么做，那她就不该是独属于我的阳光。","id":833,"figure":"https://media.prts.wiki/5/5e/Avg_avg_npc_243.png"},{"type":"character","name":"avg_npc_177","name2":"avg_npc_243","focus":"1","id":834},{"type":"dialogue","name":"管家","text":"你......","id":835,"figure":"https://media.prts.wiki/a/ae/Avg_avg_npc_177.png"},{"type":"dialog","id":836},{"type":"playsound","key":"$d_gen_walk_n","id":837},{"type":"character","name":"avg_npc_177","name2":"char_empty","fadetime":"1.5","id":838},{"type":"delay","time":"2","id":839},{"type":"dialogue","name":"管家","text":"阳光......","id":840,"figure":"https://media.prts.wiki/a/ae/Avg_avg_npc_177.png"},{"type":"dialog","id":841},{"type":"character","fadetime":"1.5","id":842},{"type":"delay","time":"2","id":843},{"type":"text","text":"康塞尔望向西方，夕阳辉煌的光芒斜射在亚利桑那宅邸的地板上。","id":844},{"type":"text","text":"一些旧时的回忆涌上心头。","id":845},{"type":"character","name":"avg_npc_177","id":846},{"type":"dialogue","name":"管家","text":"亨利，你女儿和你可真像啊......","id":847,"figure":"https://media.prts.wiki/a/ae/Avg_avg_npc_177.png"},{"type":"dialog","id":848},{"type":"blocker","a":"0","r":"0","g":"0","b":"0","fadetime":"0","block":"true","id":849},{"type":"blocker","a":"1","r":"0","g":"0","b":"0","fadetime":"1","block":"true","id":850},{"type":"stopmusic","fadetime":"1","id":851},{"type":"character","id":852},{"type":"image","id":853}],"characters":["管家","女仆","？？？","格蕾丝","聒噪的老人","彬彬有礼的先生","医生","陌生的镇民","聚集起来的镇民们"]}